[{"id": "bags-acorn-pochette-139", "name": "acorn pochette", "rawCategory": "Bags", "category": "Bags", "hexBase": "1D44", "image": "https://nh-cdn.catalogue.ac/ClosetIcon/BagShoulderAcorn0.png", "variants": [{"name": "Default", "hex": "1D44", "hexBase": "1D44", "hexVariated": "1D44", "image": "https://nh-cdn.catalogue.ac/ClosetIcon/BagShoulderAcorn0.png", "filename": "BagShoulderAcorn0", "color1": "Brown", "color2": "Green"}], "tags": ["Cute", "fairy tale", "Brown", "Green", "Not for sale", "DIY"], "size": "", "catalog": "Not for sale", "hhaConcept1": "", "hhaConcept2": "", "hhaSeries": "", "hhaSet": "", "diy": "Yes"}, {"id": "bags-apparel-shop-paper-bag-140", "name": "apparel-shop paper bag", "rawCategory": "Bags", "category": "Bags", "hexBase": "3A16", "image": "https://nh-cdn.catalogue.ac/FtrIcon/ToolBagPaperfashion0.png", "variants": [{"name": "Pink", "hex": "3A16", "hexBase": "3A16", "hexVariated": "3A16", "image": "https://nh-cdn.catalogue.ac/FtrIcon/ToolBagPaperfashion0.png", "filename": "ToolBagPaperfashion0", "color1": "White", "color2": "Pink"}, {"name": "Light blue", "hex": "0132", "hexBase": "3A16", "hexVariated": "0132", "image": "https://nh-cdn.catalogue.ac/FtrIcon/ToolBagPaperfashion1.png", "filename": "ToolBagPaperfashion1", "color1": "White", "color2": "Aqua"}], "tags": ["Simple", "Elegant", "everyday", "White", "Pink", "For sale", "Aqua"], "size": "", "catalog": "For sale", "hhaConcept1": "", "hhaConcept2": "", "hhaSeries": "", "hhaSet": "", "diy": "No"}, {"id": "bags-asian-style-clasp-purse-141", "name": "Asian-style clasp purse", "rawCategory": "Bags", "category": "Bags", "hexBase": "3A0B", "image": "https://nh-cdn.catalogue.ac/ClosetIcon/BagShoulderGamaguchiAsian0.png", "variants": [{"name": "Black", "hex": "3A0B", "hexBase": "3A0B", "hexVariated": "3A0B", "image": "https://nh-cdn.catalogue.ac/ClosetIcon/BagShoulderGamaguchiAsian0.png", "filename": "BagShoulderGamaguchiAsian0", "color1": "Black", "color2": "Red"}, {"name": "Blue", "hex": "0160", "hexBase": "3A0B", "hexVariated": "0160", "image": "https://nh-cdn.catalogue.ac/ClosetIcon/BagShoulderGamaguchiAsian1.png", "filename": "BagShoulderGamaguchiAsian1", "color1": "Blue", "color2": "Yellow"}], "tags": ["Simple", "Cute", "everyday", "Black", "Red", "For sale", "Blue", "Yellow"], "size": "", "catalog": "For sale", "hhaConcept1": "", "hhaConcept2": "", "hhaSeries": "", "hhaSet": "", "diy": "No"}, {"id": "bags-basket-bag-142", "name": "basket bag", "rawCategory": "Bags", "category": "Bags", "hexBase": "39C7", "image": "https://nh-cdn.catalogue.ac/FtrIcon/ToolBagBasket0.png", "variants": [{"name": "Light brown", "hex": "39C7", "hexBase": "39C7", "hexVariated": "39C7", "image": "https://nh-cdn.catalogue.ac/FtrIcon/ToolBagBasket0.png", "filename": "ToolBagBasket0", "color1": "Beige", "color2": "Beige"}, {"name": "Brown", "hex": "0171", "hexBase": "39C7", "hexVariated": "0171", "image": "https://nh-cdn.catalogue.ac/FtrIcon/ToolBagBasket2.png", "filename": "ToolBagBasket2", "color1": "Brown", "color2": "Brown"}, {"name": "White", "hex": "0170", "hexBase": "39C7", "hexVariated": "0170", "image": "https://nh-cdn.catalogue.ac/FtrIcon/ToolBagBasket1.png", "filename": "ToolBagBasket1", "color1": "White", "color2": "White"}], "tags": ["Simple", "Cute", "fairy tale", "vacation", "Beige", "For sale", "Brown", "White"], "size": "", "catalog": "For sale", "hhaConcept1": "", "hhaConcept2": "", "hhaSeries": "", "hhaSet": "", "diy": "No"}, {"id": "bags-basket-pack-143", "name": "basket pack", "rawCategory": "Bags", "category": "Bags", "hexBase": "1D52", "image": "https://nh-cdn.catalogue.ac/ClosetIcon/BagBackpackBasket0.png", "variants": [{"name": "Default", "hex": "1D52", "hexBase": "1D52", "hexVariated": "1D52", "image": "https://nh-cdn.catalogue.ac/ClosetIcon/BagBackpackBasket0.png", "filename": "BagBackpackBasket0", "color1": "Green", "color2": "Green"}], "tags": ["Simple", "outdoorsy", "work", "Green", "Not for sale", "DIY"], "size": "", "catalog": "Not for sale", "hhaConcept1": "", "hhaConcept2": "", "hhaSeries": "", "hhaSet": "", "diy": "Yes"}, {"id": "bags-beaded-clasp-purse-144", "name": "beaded clasp purse", "rawCategory": "Bags", "category": "Bags", "hexBase": "0164", "image": "https://nh-cdn.catalogue.ac/ClosetIcon/BagShoulderGamaguchiBijou0.png", "variants": [{"name": "Purple", "hex": "3A0D", "hexBase": "0164", "hexVariated": "3A0D", "image": "https://nh-cdn.catalogue.ac/ClosetIcon/BagShoulderGamaguchiBijou0.png", "filename": "BagShoulderGamaguchiBijou0", "color1": "Purple", "color2": "Pink"}, {"name": "Pink", "hex": "0163", "hexBase": "0164", "hexVariated": "0163", "image": "https://nh-cdn.catalogue.ac/ClosetIcon/BagShoulderGamaguchiBijou1.png", "filename": "BagShoulderGamaguchiBijou1", "color1": "Pink", "color2": "Beige"}, {"name": "Navy blue", "hex": "0164", "hexBase": "0164", "hexVariated": "0164", "image": "https://nh-cdn.catalogue.ac/ClosetIcon/BagShoulderGamaguchiBijou2.png", "filename": "BagShoulderGamaguchiBijou2", "color1": "Black", "color2": "Gray"}], "tags": ["Simple", "Elegant", "everyday", "Purple", "Pink", "For sale", "Beige", "Black", "Gray"], "size": "", "catalog": "For sale", "hhaConcept1": "", "hhaConcept2": "", "hhaSeries": "", "hhaSet": "", "diy": "No"}, {"id": "bags-bear-backpack-145", "name": "bear backpack", "rawCategory": "Bags", "category": "Bags", "hexBase": "324D", "image": "https://nh-cdn.catalogue.ac/ClosetIcon/BagBackpackBear0.png", "variants": [{"name": "Brown", "hex": "324D", "hexBase": "324D", "hexVariated": "324D", "image": "https://nh-cdn.catalogue.ac/ClosetIcon/BagBackpackBear0.png", "filename": "BagBackpackBear0", "color1": "Beige", "color2": "Red"}, {"name": "White", "hex": "0153", "hexBase": "324D", "hexVariated": "0153", "image": "https://nh-cdn.catalogue.ac/ClosetIcon/BagBackpackBear1.png", "filename": "BagBackpackBear1", "color1": "White", "color2": "Blue"}, {"name": "Pink", "hex": "02CA", "hexBase": "324D", "hexVariated": "02CA", "image": "https://nh-cdn.catalogue.ac/ClosetIcon/BagBackpackBear2.png", "filename": "BagBackpackBear2", "color1": "Pink", "color2": "Aqua"}, {"name": "Light blue", "hex": "02CE", "hexBase": "324D", "hexVariated": "02CE", "image": "https://nh-cdn.catalogue.ac/ClosetIcon/BagBackpackBear3.png", "filename": "BagBackpackBear3", "color1": "Aqua", "color2": "Yellow"}, {"name": "Black", "hex": "02CF", "hexBase": "324D", "hexVariated": "02CF", "image": "https://nh-cdn.catalogue.ac/ClosetIcon/BagBackpackBear4.png", "filename": "BagBackpackBear4", "color1": "Black", "color2": "Purple"}], "tags": ["Cute", "fairy tale", "Beige", "Red", "For sale", "White", "Blue", "Pink", "Aqua", "Yellow", "Black", "Purple"], "size": "", "catalog": "For sale", "hhaConcept1": "", "hhaConcept2": "", "hhaSeries": "", "hhaSet": "", "diy": "No"}, {"id": "bags-botanical-print-backpack-146", "name": "botanical-print backpack", "rawCategory": "Bags", "category": "Bags", "hexBase": "02A3", "image": "https://nh-cdn.catalogue.ac/ClosetIcon/BagBackpackTownPattern0.png", "variants": [{"name": "Black", "hex": "39BE", "hexBase": "02A3", "hexVariated": "39BE", "image": "https://nh-cdn.catalogue.ac/ClosetIcon/BagBackpackTownPattern0.png", "filename": "BagBackpackTownPattern0", "color1": "Yellow", "color2": "Green"}, {"name": "White", "hex": "02A3", "hexBase": "02A3", "hexVariated": "02A3", "image": "https://nh-cdn.catalogue.ac/ClosetIcon/BagBackpackTownPattern1.png", "filename": "BagBackpackTownPattern1", "color1": "Red", "color2": "Green"}], "tags": ["Simple", "Active", "everyday", "Yellow", "Green", "For sale", "Red"], "size": "", "catalog": "For sale", "hhaConcept1": "", "hhaConcept2": "", "hhaSeries": "", "hhaSet": "", "diy": "No"}, {"id": "bags-bread-print-eco-bag-147", "name": "bread-print eco bag", "rawCategory": "Bags", "category": "Bags", "hexBase": "39DD", "image": "https://nh-cdn.catalogue.ac/FtrIcon/ToolBagEcobread0.png", "variants": [{"name": "Default", "hex": "39DD", "hexBase": "39DD", "hexVariated": "39DD", "image": "https://nh-cdn.catalogue.ac/FtrIcon/ToolBagEcobread0.png", "filename": "ToolBagEcobread0", "color1": "White", "color2": "Beige"}], "tags": ["Simple", "Active", "everyday", "White", "Beige", "For sale"], "size": "", "catalog": "For sale", "hhaConcept1": "", "hhaConcept2": "", "hhaSeries": "", "hhaSet": "", "diy": "No"}, {"id": "bags-bug-cage-148", "name": "bug cage", "rawCategory": "Bags", "category": "Bags", "hexBase": "1D37", "image": "https://nh-cdn.catalogue.ac/ClosetIcon/BagShoulderCage0.png", "variants": [{"name": "Default", "hex": "1D37", "hexBase": "1D37", "hexVariated": "1D37", "image": "https://nh-cdn.catalogue.ac/ClosetIcon/BagShoulderCage0.png", "filename": "BagShoulderCage0", "color1": "Green", "color2": "White"}], "tags": ["Active", "outdoorsy", "vacation", "Green", "White", "Not for sale"], "size": "", "catalog": "Not for sale", "hhaConcept1": "", "hhaConcept2": "", "hhaSeries": "", "hhaSet": "", "diy": "No"}, {"id": "bags-bunny-day-bag-149", "name": "Bunny Day bag", "rawCategory": "Bags", "category": "Bags", "hexBase": "309F", "image": "https://nh-cdn.catalogue.ac/ClosetIcon/BagBackpackEgg0.png", "variants": [{"name": "Default", "hex": "309F", "hexBase": "309F", "hexVariated": "309F", "image": "https://nh-cdn.catalogue.ac/ClosetIcon/BagBackpackEgg0.png", "filename": "BagBackpackEgg0", "color1": "Colorful", "color2": "Colorful"}], "tags": ["Active", "Cute", "fairy tale", "party", "theatrical", "Colorful", "Not for sale", "DIY"], "size": "", "catalog": "Not for sale", "hhaConcept1": "", "hhaConcept2": "", "hhaSeries": "", "hhaSet": "", "diy": "Yes"}, {"id": "bags-butterfly-backpack-150", "name": "butterfly backpack", "rawCategory": "Bags", "category": "Bags", "hexBase": "1D4E", "image": "https://nh-cdn.catalogue.ac/ClosetIcon/BagBackpackButterfly0.png", "variants": [{"name": "Default", "hex": "1D4E", "hexBase": "1D4E", "hexVariated": "1D4E", "image": "https://nh-cdn.catalogue.ac/ClosetIcon/BagBackpackButterfly0.png", "filename": "BagBackpackButterfly0", "color1": "Pink", "color2": "Yellow"}], "tags": ["Cute", "everyday", "fairy tale", "theatrical", "Pink", "Yellow", "Not for sale"], "size": "", "catalog": "Not for sale", "hhaConcept1": "", "hhaConcept2": "", "hhaSeries": "", "hhaSet": "", "diy": "No"}, {"id": "bags-camo-tote-bag-151", "name": "camo tote bag", "rawCategory": "Bags", "category": "Bags", "hexBase": "3A2A", "image": "https://nh-cdn.catalogue.ac/FtrIcon/ToolBagTotecamouflage0.png", "variants": [{"name": "Green", "hex": "3A2A", "hexBase": "3A2A", "hexVariated": "3A2A", "image": "https://nh-cdn.catalogue.ac/FtrIcon/ToolBagTotecamouflage0.png", "filename": "ToolBagTotecamouflage0", "color1": "Green", "color2": "Black"}, {"name": "Brown", "hex": "016F", "hexBase": "3A2A", "hexVariated": "016F", "image": "https://nh-cdn.catalogue.ac/FtrIcon/ToolBagTotecamouflage1.png", "filename": "ToolBagTotecamouflage1", "color1": "Brown", "color2": "Black"}], "tags": ["Simple", "Active", "everyday", "outdoorsy", "Green", "Black", "For sale", "Brown"], "size": "", "catalog": "For sale", "hhaConcept1": "", "hhaConcept2": "", "hhaSeries": "", "hhaSet": "", "diy": "No"}, {"id": "bags-canvas-backpack-152", "name": "canvas backpack", "rawCategory": "Bags", "category": "Bags", "hexBase": "1D55", "image": "https://nh-cdn.catalogue.ac/ClosetIcon/BagBackpackTote0.png", "variants": [{"name": "Default", "hex": "1D55", "hexBase": "1D55", "hexVariated": "1D55", "image": "https://nh-cdn.catalogue.ac/ClosetIcon/BagBackpackTote0.png", "filename": "BagBackpackTote0", "color1": "White", "color2": "Orange"}], "tags": ["Simple", "everyday", "White", "Orange", "For sale"], "size": "", "catalog": "For sale", "hhaConcept1": "", "hhaConcept2": "", "hhaSeries": "", "hhaSet": "", "diy": "No"}, {"id": "bags-checkered-backpack-153", "name": "checkered backpack", "rawCategory": "Bags", "category": "Bags", "hexBase": "02BF", "image": "https://nh-cdn.catalogue.ac/ClosetIcon/BagBackpackTownCheck2.png", "variants": [{"name": "Gray", "hex": "02BE", "hexBase": "02BF", "hexVariated": "02BE", "image": "https://nh-cdn.catalogue.ac/ClosetIcon/BagBackpackTownCheck2.png", "filename": "BagBackpackTownCheck2", "color1": "Gray", "color2": "Brown"}, {"name": "Green", "hex": "02BF", "hexBase": "02BF", "hexVariated": "02BF", "image": "https://nh-cdn.catalogue.ac/ClosetIcon/BagBackpackTownCheck3.png", "filename": "BagBackpackTownCheck3", "color1": "Green", "color2": "Brown"}, {"name": "Blue", "hex": "02BD", "hexBase": "02BF", "hexVariated": "02BD", "image": "https://nh-cdn.catalogue.ac/ClosetIcon/BagBackpackTownCheck1.png", "filename": "BagBackpackTownCheck1", "color1": "Aqua", "color2": "Brown"}, {"name": "Brown", "hex": "39FC", "hexBase": "02BF", "hexVariated": "39FC", "image": "https://nh-cdn.catalogue.ac/ClosetIcon/BagBackpackTownCheck0.png", "filename": "BagBackpackTownCheck0", "color1": "Brown", "color2": "Brown"}], "tags": ["Simple", "Active", "everyday", "Gray", "Brown", "For sale", "Green", "Aqua"], "size": "", "catalog": "For sale", "hhaConcept1": "", "hhaConcept2": "", "hhaSeries": "", "hhaSet": "", "diy": "No"}, {"id": "bags-cherry-blossom-pochette-154", "name": "cherry-blossom pochette", "rawCategory": "Bags", "category": "Bags", "hexBase": "1D42", "image": "https://nh-cdn.catalogue.ac/ClosetIcon/BagShoulderCherryblossoms0.png", "variants": [{"name": "Default", "hex": "1D42", "hexBase": "1D42", "hexVariated": "1D42", "image": "https://nh-cdn.catalogue.ac/ClosetIcon/BagShoulderCherryblossoms0.png", "filename": "BagShoulderCherryblossoms0", "color1": "Pink", "color2": "Pink"}], "tags": ["Cute", "fairy tale", "vacation", "Pink", "Not for sale", "DIY"], "size": "", "catalog": "Not for sale", "hhaConcept1": "", "hhaConcept2": "", "hhaSeries": "", "hhaSet": "", "diy": "Yes"}, {"id": "bags-clasp-purse-155", "name": "clasp purse", "rawCategory": "Bags", "category": "Bags", "hexBase": "015B", "image": "https://nh-cdn.catalogue.ac/ClosetIcon/BagShoulderGamaguchi4.png", "variants": [{"name": "White", "hex": "0159", "hexBase": "015B", "hexVariated": "0159", "image": "https://nh-cdn.catalogue.ac/ClosetIcon/BagShoulderGamaguchi4.png", "filename": "BagShoulderGamaguchi4", "color1": "White", "color2": "Yellow"}, {"name": "Ash", "hex": "015A", "hexBase": "015B", "hexVariated": "015A", "image": "https://nh-cdn.catalogue.ac/ClosetIcon/BagShoulderGamaguchi5.png", "filename": "BagShoulderGamaguchi5", "color1": "Gray", "color2": "Yellow"}, {"name": "Red", "hex": "0154", "hexBase": "015B", "hexVariated": "0154", "image": "https://nh-cdn.catalogue.ac/ClosetIcon/BagShoulderGamaguchi1.png", "filename": "BagShoulderGamaguchi1", "color1": "Red", "color2": "Yellow"}, {"name": "Green", "hex": "0158", "hexBase": "015B", "hexVariated": "0158", "image": "https://nh-cdn.catalogue.ac/ClosetIcon/BagShoulderGamaguchi3.png", "filename": "BagShoulderGamaguchi3", "color1": "Green", "color2": "Yellow"}, {"name": "Blue", "hex": "0156", "hexBase": "015B", "hexVariated": "0156", "image": "https://nh-cdn.catalogue.ac/ClosetIcon/BagShoulderGamaguchi2.png", "filename": "BagShoulderGamaguchi2", "color1": "Blue", "color2": "Yellow"}, {"name": "Brown", "hex": "015B", "hexBase": "015B", "hexVariated": "015B", "image": "https://nh-cdn.catalogue.ac/ClosetIcon/BagShoulderGamaguchi6.png", "filename": "BagShoulderGamaguchi6", "color1": "Brown", "color2": "Yellow"}, {"name": "Yellow", "hex": "39BF", "hexBase": "015B", "hexVariated": "39BF", "image": "https://nh-cdn.catalogue.ac/ClosetIcon/BagShoulderGamaguchi0.png", "filename": "BagShoulderGamaguchi0", "color1": "Brown", "color2": "Yellow"}], "tags": ["Simple", "everyday", "White", "Yellow", "For sale", "Gray", "Red", "Green", "Blue", "Brown"], "size": "", "catalog": "For sale", "hhaConcept1": "", "hhaConcept2": "", "hhaSeries": "", "hhaSet": "", "diy": "No"}, {"id": "bags-cloth-shoulder-bag-156", "name": "cloth shoulder bag", "rawCategory": "Bags", "category": "Bags", "hexBase": "2EEE", "image": "https://nh-cdn.catalogue.ac/ClosetIcon/BagShoulderCanvas2.png", "variants": [{"name": "Ivory", "hex": "2EEE", "hexBase": "2EEE", "hexVariated": "2EEE", "image": "https://nh-cdn.catalogue.ac/ClosetIcon/BagShoulderCanvas2.png", "filename": "BagShoulderCanvas2", "color1": "White", "color2": "White"}, {"name": "Orange", "hex": "2EED", "hexBase": "2EEE", "hexVariated": "2EED", "image": "https://nh-cdn.catalogue.ac/ClosetIcon/BagShoulderCanvas1.png", "filename": "BagShoulderCanvas1", "color1": "Orange", "color2": "Orange"}, {"name": "Blue", "hex": "1D3F", "hexBase": "2EEE", "hexVariated": "1D3F", "image": "https://nh-cdn.catalogue.ac/ClosetIcon/BagShoulderCanvas0.png", "filename": "BagShoulderCanvas0", "color1": "Aqua", "color2": "Aqua"}], "tags": ["Simple", "everyday", "White", "For sale", "Orange", "Aqua"], "size": "", "catalog": "For sale", "hhaConcept1": "", "hhaConcept2": "", "hhaSeries": "", "hhaSet": "", "diy": "No"}, {"id": "bags-clutch-157", "name": "clutch", "rawCategory": "Bags", "category": "Bags", "hexBase": "39C8", "image": "https://nh-cdn.catalogue.ac/FtrIcon/ToolBagSecond0.png", "variants": [{"name": "Light brown", "hex": "39C8", "hexBase": "39C8", "hexVariated": "39C8", "image": "https://nh-cdn.catalogue.ac/FtrIcon/ToolBagSecond0.png", "filename": "ToolBagSecond0", "color1": "Brown", "color2": "Gray"}, {"name": "Black", "hex": "0135", "hexBase": "39C8", "hexVariated": "0135", "image": "https://nh-cdn.catalogue.ac/FtrIcon/ToolBagSecond3.png", "filename": "ToolBagSecond3", "color1": "Black", "color2": "Gray"}, {"name": "Red", "hex": "0134", "hexBase": "39C8", "hexVariated": "0134", "image": "https://nh-cdn.catalogue.ac/FtrIcon/ToolBagSecond2.png", "filename": "ToolBagSecond2", "color1": "Red", "color2": "Gray"}, {"name": "Green", "hex": "0133", "hexBase": "39C8", "hexVariated": "0133", "image": "https://nh-cdn.catalogue.ac/FtrIcon/ToolBagSecond1.png", "filename": "ToolBagSecond1", "color1": "Green", "color2": "Gray"}], "tags": ["Cool", "Simple", "formal", "party", "work", "Brown", "Gray", "For sale", "Black", "Red", "Green"], "size": "", "catalog": "For sale", "hhaConcept1": "", "hhaConcept2": "", "hhaSeries": "", "hhaSet": "", "diy": "No"}, {"id": "bags-crossbody-bag-158", "name": "crossbody bag", "rawCategory": "Bags", "category": "Bags", "hexBase": "2ECE", "image": "https://nh-cdn.catalogue.ac/ClosetIcon/BagBackpackBody3.png", "variants": [{"name": "White", "hex": "2ECE", "hexBase": "2ECE", "hexVariated": "2ECE", "image": "https://nh-cdn.catalogue.ac/ClosetIcon/BagBackpackBody3.png", "filename": "BagBackpackBody3", "color1": "White", "color2": "Black"}, {"name": "Pink", "hex": "1D3B", "hexBase": "2ECE", "hexVariated": "1D3B", "image": "https://nh-cdn.catalogue.ac/ClosetIcon/BagBackpackBody0.png", "filename": "BagBackpackBody0", "color1": "Pink", "color2": "Black"}, {"name": "Yellow", "hex": "2ECD", "hexBase": "2ECE", "hexVariated": "2ECD", "image": "https://nh-cdn.catalogue.ac/ClosetIcon/BagBackpackBody2.png", "filename": "BagBackpackBody2", "color1": "Yellow", "color2": "Black"}, {"name": "Green", "hex": "2ECC", "hexBase": "2ECE", "hexVariated": "2ECC", "image": "https://nh-cdn.catalogue.ac/ClosetIcon/BagBackpackBody1.png", "filename": "BagBackpackBody1", "color1": "Green", "color2": "Black"}], "tags": ["Active", "Simple", "everyday", "outdoorsy", "sporty", "White", "Black", "For sale", "Pink", "Yellow", "Green"], "size": "", "catalog": "For sale", "hhaConcept1": "", "hhaConcept2": "", "hhaSeries": "", "hhaSet": "", "diy": "No"}, {"id": "bags-crossbody-boston-bag-159", "name": "crossbody boston bag", "rawCategory": "Bags", "category": "Bags", "hexBase": "2EEB", "image": "https://nh-cdn.catalogue.ac/ClosetIcon/BagShoulderDrum0.png", "variants": [{"name": "Red", "hex": "1D3D", "hexBase": "2EEB", "hexVariated": "1D3D", "image": "https://nh-cdn.catalogue.ac/ClosetIcon/BagShoulderDrum0.png", "filename": "BagShoulderDrum0", "color1": "Red", "color2": "Black"}, {"name": "Blue", "hex": "2EEB", "hexBase": "2EEB", "hexVariated": "2EEB", "image": "https://nh-cdn.catalogue.ac/ClosetIcon/BagShoulderDrum1.png", "filename": "BagShoulderDrum1", "color1": "Blue", "color2": "Black"}], "tags": ["Simple", "Active", "everyday", "outdoorsy", "sporty", "Red", "Black", "For sale", "Blue"], "size": "", "catalog": "For sale", "hhaConcept1": "", "hhaConcept2": "", "hhaSeries": "", "hhaSet": "", "diy": "No"}, {"id": "bags-dal-backpack-160", "name": "DAL backpack", "rawCategory": "Bags", "category": "Bags", "hexBase": "2F63", "image": "https://nh-cdn.catalogue.ac/ClosetIcon/BagBackpackDal0.png", "variants": [{"name": "Default", "hex": "2F63", "hexBase": "2F63", "hexVariated": "2F63", "image": "https://nh-cdn.catalogue.ac/ClosetIcon/BagBackpackDal0.png", "filename": "BagBackpackDal0", "color1": "Blue", "color2": "Black"}], "tags": ["Cool", "Active", "outdoorsy", "vacation", "Blue", "Black", "Not for sale"], "size": "", "catalog": "Not for sale", "hhaConcept1": "", "hhaConcept2": "", "hhaSeries": "", "hhaSet": "", "diy": "No"}, {"id": "bags-delivery-bag-161", "name": "delivery bag", "rawCategory": "Bags", "category": "Bags", "hexBase": "385A", "image": "https://nh-cdn.catalogue.ac/ClosetIcon/BagBackpackDelivery0.png", "variants": [{"name": "Black", "hex": "385A", "hexBase": "385A", "hexVariated": "385A", "image": "https://nh-cdn.catalogue.ac/ClosetIcon/BagBackpackDelivery0.png", "filename": "BagBackpackDelivery0", "color1": "Black", "color2": "Yellow"}, {"name": "Pink", "hex": "01EF", "hexBase": "385A", "hexVariated": "01EF", "image": "https://nh-cdn.catalogue.ac/ClosetIcon/BagBackpackDelivery5.png", "filename": "BagBackpackDelivery5", "color1": "Pink", "color2": "Aqua"}, {"name": "Yellow", "hex": "01ED", "hexBase": "385A", "hexVariated": "01ED", "image": "https://nh-cdn.catalogue.ac/ClosetIcon/BagBackpackDelivery3.png", "filename": "BagBackpackDelivery3", "color1": "Yellow", "color2": "Green"}, {"name": "Green", "hex": "01EC", "hexBase": "385A", "hexVariated": "01EC", "image": "https://nh-cdn.catalogue.ac/ClosetIcon/BagBackpackDelivery2.png", "filename": "BagBackpackDelivery2", "color1": "Green", "color2": "Orange"}, {"name": "Blue", "hex": "01EB", "hexBase": "385A", "hexVariated": "01EB", "image": "https://nh-cdn.catalogue.ac/ClosetIcon/BagBackpackDelivery1.png", "filename": "BagBackpackDelivery1", "color1": "Blue", "color2": "Black"}, {"name": "Brown", "hex": "01EE", "hexBase": "385A", "hexVariated": "01EE", "image": "https://nh-cdn.catalogue.ac/ClosetIcon/BagBackpackDelivery4.png", "filename": "BagBackpackDelivery4", "color1": "Brown", "color2": "Beige"}], "tags": ["Simple", "Active", "work", "Black", "Yellow", "For sale", "Pink", "Aqua", "Green", "Orange", "Blue", "Brown", "Beige"], "size": "", "catalog": "For sale", "hhaConcept1": "", "hhaConcept2": "", "hhaSeries": "", "hhaSet": "", "diy": "No"}, {"id": "bags-department-store-paper-bag-162", "name": "department-store paper bag", "rawCategory": "Bags", "category": "Bags", "hexBase": "0131", "image": "https://nh-cdn.catalogue.ac/FtrIcon/ToolBagPaperflower0.png", "variants": [{"name": "Blue", "hex": "3A18", "hexBase": "0131", "hexVariated": "3A18", "image": "https://nh-cdn.catalogue.ac/FtrIcon/ToolBagPaperflower0.png", "filename": "ToolBagPaperflower0", "color1": "White", "color2": "Blue"}, {"name": "Red", "hex": "0131", "hexBase": "0131", "hexVariated": "0131", "image": "https://nh-cdn.catalogue.ac/FtrIcon/ToolBagPaperflower1.png", "filename": "ToolBagPaperflower1", "color1": "White", "color2": "Red"}], "tags": ["Simple", "Elegant", "everyday", "White", "Blue", "For sale", "Red"], "size": "", "catalog": "For sale", "hhaConcept1": "", "hhaConcept2": "", "hhaSeries": "", "hhaSet": "", "diy": "No"}, {"id": "bags-diamond-weave-basket-bag-163", "name": "diamond-weave basket bag", "rawCategory": "Bags", "category": "Bags", "hexBase": "3A06", "image": "https://nh-cdn.catalogue.ac/FtrIcon/ToolBagBasketdiagram0.png", "variants": [{"name": "Default", "hex": "3A06", "hexBase": "3A06", "hexVariated": "3A06", "image": "https://nh-cdn.catalogue.ac/FtrIcon/ToolBagBasketdiagram0.png", "filename": "ToolBagBasketdiagram0", "color1": "Beige", "color2": "Green"}], "tags": ["Simple", "Cute", "everyday", "fairy tale", "vacation", "Beige", "Green", "For sale"], "size": "", "catalog": "For sale", "hhaConcept1": "", "hhaConcept2": "", "hhaSeries": "", "hhaSet": "", "diy": "No"}, {"id": "bags-dreamy-backpack-164", "name": "dreamy backpack", "rawCategory": "Bags", "category": "Bags", "hexBase": "39F6", "image": "https://nh-cdn.catalogue.ac/ClosetIcon/BagBackpackTownYumekawa0.png", "variants": [{"name": "Pink", "hex": "39F6", "hexBase": "39F6", "hexVariated": "39F6", "image": "https://nh-cdn.catalogue.ac/ClosetIcon/BagBackpackTownYumekawa0.png", "filename": "BagBackpackTownYumekawa0", "color1": "Pink", "color2": "Purple"}, {"name": "Mint", "hex": "02A7", "hexBase": "39F6", "hexVariated": "02A7", "image": "https://nh-cdn.catalogue.ac/ClosetIcon/BagBackpackTownYumekawa1.png", "filename": "BagBackpackTownYumekawa1", "color1": "Green", "color2": "Purple"}], "tags": ["Simple", "Active", "everyday", "fairy tale", "Pink", "Purple", "For sale", "Green"], "size": "", "catalog": "For sale", "hhaConcept1": "", "hhaConcept2": "", "hhaSeries": "", "hhaSet": "", "diy": "No"}, {"id": "bags-dreamy-pochette-165", "name": "dreamy pochette", "rawCategory": "Bags", "category": "Bags", "hexBase": "39E9", "image": "https://nh-cdn.catalogue.ac/ClosetIcon/BagShoulderYumekawa0.png", "variants": [{"name": "Default", "hex": "39E9", "hexBase": "39E9", "hexVariated": "39E9", "image": "https://nh-cdn.catalogue.ac/ClosetIcon/BagShoulderYumekawa0.png", "filename": "BagShoulderYumekawa0", "color1": "Pink", "color2": "Aqua"}], "tags": ["Cute", "everyday", "fairy tale", "Pink", "Aqua", "For sale"], "size": "", "catalog": "For sale", "hhaConcept1": "", "hhaConcept2": "", "hhaSeries": "", "hhaSet": "", "diy": "No"}, {"id": "bags-dreamy-ribbon-pochette-166", "name": "dreamy ribbon pochette", "rawCategory": "Bags", "category": "Bags", "hexBase": "3A23", "image": "https://nh-cdn.catalogue.ac/ClosetIcon/BagShoulderYumekawaRibbon0.png", "variants": [{"name": "Default", "hex": "3A23", "hexBase": "3A23", "hexVariated": "3A23", "image": "https://nh-cdn.catalogue.ac/ClosetIcon/BagShoulderYumekawaRibbon0.png", "filename": "BagShoulderYumekawaRibbon0", "color1": "Pink", "color2": "Pink"}], "tags": ["Cute", "everyday", "fairy tale", "Pink", "For sale"], "size": "", "catalog": "For sale", "hhaConcept1": "", "hhaConcept2": "", "hhaSeries": "", "hhaSet": "", "diy": "No"}, {"id": "bags-dreamy-unicorn-pochette-167", "name": "dreamy unicorn pochette", "rawCategory": "Bags", "category": "Bags", "hexBase": "3A24", "image": "https://nh-cdn.catalogue.ac/ClosetIcon/BagShoulderYumekawaUnicorn0.png", "variants": [{"name": "Default", "hex": "3A24", "hexBase": "3A24", "hexVariated": "3A24", "image": "https://nh-cdn.catalogue.ac/ClosetIcon/BagShoulderYumekawaUnicorn0.png", "filename": "BagShoulderYumekawaUnicorn0", "color1": "Yellow", "color2": "Pink"}], "tags": ["Cute", "everyday", "fairy tale", "Yellow", "Pink", "For sale"], "size": "", "catalog": "For sale", "hhaConcept1": "", "hhaConcept2": "", "hhaSeries": "", "hhaSet": "", "diy": "No"}, {"id": "bags-dry-bag-168", "name": "dry bag", "rawCategory": "Bags", "category": "Bags", "hexBase": "2EBC", "image": "https://nh-cdn.catalogue.ac/ClosetIcon/BagBackpackDry0.png", "variants": [{"name": "Yellow", "hex": "1D2F", "hexBase": "2EBC", "hexVariated": "1D2F", "image": "https://nh-cdn.catalogue.ac/ClosetIcon/BagBackpackDry0.png", "filename": "BagBackpackDry0", "color1": "Yellow", "color2": "Black"}, {"name": "Blue", "hex": "2EBC", "hexBase": "2EBC", "hexVariated": "2EBC", "image": "https://nh-cdn.catalogue.ac/ClosetIcon/BagBackpackDry1.png", "filename": "BagBackpackDry1", "color1": "Blue", "color2": "Black"}], "tags": ["Active", "outdoorsy", "sporty", "Yellow", "Black", "For sale", "Blue"], "size": "", "catalog": "For sale", "hhaConcept1": "", "hhaConcept2": "", "hhaSeries": "", "hhaSet": "", "diy": "No"}, {"id": "bags-electronics-store-paper-bag-169", "name": "electronics-store paper bag", "rawCategory": "Bags", "category": "Bags", "hexBase": "02D7", "image": "https://nh-cdn.catalogue.ac/FtrIcon/ToolBagPaperelectric0.png", "variants": [{"name": "Yellow", "hex": "3A17", "hexBase": "02D7", "hexVariated": "3A17", "image": "https://nh-cdn.catalogue.ac/FtrIcon/ToolBagPaperelectric0.png", "filename": "ToolBagPaperelectric0", "color1": "Black", "color2": "Yellow"}, {"name": "Light blue", "hex": "02D7", "hexBase": "02D7", "hexVariated": "02D7", "image": "https://nh-cdn.catalogue.ac/FtrIcon/ToolBagPaperelectric1.png", "filename": "ToolBagPaperelectric1", "color1": "Black", "color2": "Aqua"}, {"name": "Red", "hex": "02DD", "hexBase": "02D7", "hexVariated": "02DD", "image": "https://nh-cdn.catalogue.ac/FtrIcon/ToolBagPaperelectric3.png", "filename": "ToolBagPaperelectric3", "color1": "White", "color2": "Red"}, {"name": "Blue", "hex": "02DC", "hexBase": "02D7", "hexVariated": "02DC", "image": "https://nh-cdn.catalogue.ac/FtrIcon/ToolBagPaperelectric2.png", "filename": "ToolBagPaperelectric2", "color1": "White", "color2": "Blue"}], "tags": ["Simple", "everyday", "Black", "Yellow", "For sale", "Aqua", "White", "Red", "Blue"], "size": "", "catalog": "For sale", "hhaConcept1": "", "hhaConcept2": "", "hhaSeries": "", "hhaSet": "", "diy": "No"}, {"id": "bags-evening-bag-170", "name": "evening bag", "rawCategory": "Bags", "category": "Bags", "hexBase": "1C89", "image": "https://nh-cdn.catalogue.ac/ClosetIcon/BagShoulderParty2.png", "variants": [{"name": "Black", "hex": "2EC9", "hexBase": "1C89", "hexVariated": "2EC9", "image": "https://nh-cdn.catalogue.ac/ClosetIcon/BagShoulderParty2.png", "filename": "BagShoulderParty2", "color1": "Black", "color2": "Yellow"}, {"name": "Pink", "hex": "1C89", "hexBase": "1C89", "hexVariated": "1C89", "image": "https://nh-cdn.catalogue.ac/ClosetIcon/BagShoulderParty0.png", "filename": "BagShoulderParty0", "color1": "Pink", "color2": "Yellow"}, {"name": "Blue", "hex": "2EC8", "hexBase": "1C89", "hexVariated": "2EC8", "image": "https://nh-cdn.catalogue.ac/ClosetIcon/BagShoulderParty1.png", "filename": "BagShoulderParty1", "color1": "Blue", "color2": "Yellow"}], "tags": ["Cute", "Elegant", "formal", "party", "Black", "Yellow", "For sale", "Pink", "Blue"], "size": "", "catalog": "For sale", "hhaConcept1": "", "hhaConcept2": "", "hhaSeries": "", "hhaSet": "", "diy": "No"}, {"id": "bags-extra-large-backpack-171", "name": "extra-large backpack", "rawCategory": "Bags", "category": "Bags", "hexBase": "1D51", "image": "https://nh-cdn.catalogue.ac/ClosetIcon/BagBackpackMountain2.png", "variants": [{"name": "Black", "hex": "2EC4", "hexBase": "1D51", "hexVariated": "2EC4", "image": "https://nh-cdn.catalogue.ac/ClosetIcon/BagBackpackMountain2.png", "filename": "BagBackpackMountain2", "color1": "Black", "color2": "Black"}, {"name": "Red", "hex": "1D51", "hexBase": "1D51", "hexVariated": "1D51", "image": "https://nh-cdn.catalogue.ac/ClosetIcon/BagBackpackMountain0.png", "filename": "BagBackpackMountain0", "color1": "Red", "color2": "Red"}, {"name": "Green", "hex": "2EC3", "hexBase": "1D51", "hexVariated": "2EC3", "image": "https://nh-cdn.catalogue.ac/ClosetIcon/BagBackpackMountain1.png", "filename": "BagBackpackMountain1", "color1": "Green", "color2": "Green"}, {"name": "Blue", "hex": "2EC5", "hexBase": "1D51", "hexVariated": "2EC5", "image": "https://nh-cdn.catalogue.ac/ClosetIcon/BagBackpackMountain3.png", "filename": "BagBackpackMountain3", "color1": "Blue", "color2": "Blue"}], "tags": ["Active", "outdoorsy", "sporty", "Black", "For sale", "Red", "Green", "Blue"], "size": "", "catalog": "For sale", "hhaConcept1": "", "hhaConcept2": "", "hhaSeries": "", "hhaSet": "", "diy": "No"}, {"id": "bags-faux-fur-bag-172", "name": "faux-fur bag", "rawCategory": "Bags", "category": "Bags", "hexBase": "1D38", "image": "https://nh-cdn.catalogue.ac/ClosetIcon/BagShoulderFakefur0.png", "variants": [{"name": "Pink", "hex": "1D38", "hexBase": "1D38", "hexVariated": "1D38", "image": "https://nh-cdn.catalogue.ac/ClosetIcon/BagShoulderFakefur0.png", "filename": "BagShoulderFakefur0", "color1": "Pink", "color2": "Yellow"}, {"name": "Purple", "hex": "2EE3", "hexBase": "1D38", "hexVariated": "2EE3", "image": "https://nh-cdn.catalogue.ac/ClosetIcon/BagShoulderFakefur1.png", "filename": "BagShoulderFakefur1", "color1": "Purple", "color2": "Yellow"}], "tags": ["Cute", "Gorgeous", "formal", "party", "Pink", "Yellow", "For sale", "Purple"], "size": "", "catalog": "For sale", "hhaConcept1": "", "hhaConcept2": "", "hhaSeries": "", "hhaSet": "", "diy": "No"}, {"id": "bags-fish-pochette-173", "name": "fish pochette", "rawCategory": "Bags", "category": "Bags", "hexBase": "1D35", "image": "https://nh-cdn.catalogue.ac/ClosetIcon/BagShoulderFish0.png", "variants": [{"name": "Default", "hex": "1D35", "hexBase": "1D35", "hexVariated": "1D35", "image": "https://nh-cdn.catalogue.ac/ClosetIcon/BagShoulderFish0.png", "filename": "BagShoulderFish0", "color1": "Aqua", "color2": "Blue"}], "tags": ["Cute", "everyday", "vacation", "Aqua", "Blue", "Not for sale"], "size": "", "catalog": "Not for sale", "hhaConcept1": "", "hhaConcept2": "", "hhaSeries": "", "hhaSet": "", "diy": "No"}, {"id": "bags-fish-print-eco-bag-174", "name": "fish-print eco bag", "rawCategory": "Bags", "category": "Bags", "hexBase": "39DC", "image": "https://nh-cdn.catalogue.ac/FtrIcon/ToolBagEcofish0.png", "variants": [{"name": "Default", "hex": "39DC", "hexBase": "39DC", "hexVariated": "39DC", "image": "https://nh-cdn.catalogue.ac/FtrIcon/ToolBagEcofish0.png", "filename": "ToolBagEcofish0", "color1": "Aqua", "color2": "Blue"}], "tags": ["Simple", "Active", "everyday", "Aqua", "Blue", "For sale"], "size": "", "catalog": "For sale", "hhaConcept1": "", "hhaConcept2": "", "hhaSeries": "", "hhaSet": "", "diy": "No"}, {"id": "bags-flower-print-eco-bag-175", "name": "flower-print eco bag", "rawCategory": "Bags", "category": "Bags", "hexBase": "39DE", "image": "https://nh-cdn.catalogue.ac/FtrIcon/ToolBagEcoflower0.png", "variants": [{"name": "Default", "hex": "39DE", "hexBase": "39DE", "hexVariated": "39DE", "image": "https://nh-cdn.catalogue.ac/FtrIcon/ToolBagEcoflower0.png", "filename": "ToolBagEcoflower0", "color1": "Green", "color2": "Pink"}], "tags": ["Simple", "Active", "everyday", "Green", "Pink", "For sale"], "size": "", "catalog": "For sale", "hhaConcept1": "", "hhaConcept2": "", "hhaSeries": "", "hhaSet": "", "diy": "No"}, {"id": "bags-foldover-top-backpack-176", "name": "foldover-top backpack", "rawCategory": "Bags", "category": "Bags", "hexBase": "1D53", "image": "https://nh-cdn.catalogue.ac/ClosetIcon/BagBackpackLid2.png", "variants": [{"name": "Gray", "hex": "2EF1", "hexBase": "1D53", "hexVariated": "2EF1", "image": "https://nh-cdn.catalogue.ac/ClosetIcon/BagBackpackLid2.png", "filename": "BagBackpackLid2", "color1": "Gray", "color2": "White"}, {"name": "Pink", "hex": "2EF2", "hexBase": "1D53", "hexVariated": "2EF2", "image": "https://nh-cdn.catalogue.ac/ClosetIcon/BagBackpackLid3.png", "filename": "BagBackpackLid3", "color1": "Pink", "color2": "Purple"}, {"name": "Green", "hex": "1D53", "hexBase": "1D53", "hexVariated": "1D53", "image": "https://nh-cdn.catalogue.ac/ClosetIcon/BagBackpackLid0.png", "filename": "BagBackpackLid0", "color1": "Green", "color2": "Beige"}, {"name": "Blue", "hex": "2EF0", "hexBase": "1D53", "hexVariated": "2EF0", "image": "https://nh-cdn.catalogue.ac/ClosetIcon/BagBackpackLid1.png", "filename": "BagBackpackLid1", "color1": "Blue", "color2": "Aqua"}], "tags": ["Active", "Simple", "outdoorsy", "sporty", "Gray", "White", "For sale", "Pink", "Purple", "Green", "Beige", "Blue", "Aqua"], "size": "", "catalog": "For sale", "hhaConcept1": "", "hhaConcept2": "", "hhaSeries": "", "hhaSet": "", "diy": "No"}, {"id": "bags-furoshiki-bag-177", "name": "furoshiki bag", "rawCategory": "Bags", "category": "Bags", "hexBase": "0230", "image": "https://nh-cdn.catalogue.ac/FtrIcon/ToolBagFuroshiki0.png", "variants": [{"name": "Green", "hex": "39C4", "hexBase": "0230", "hexVariated": "39C4", "image": "https://nh-cdn.catalogue.ac/FtrIcon/ToolBagFuroshiki0.png", "filename": "ToolBagFuroshiki0", "color1": "Green", "color2": "White"}, {"name": "White", "hex": "022F", "hexBase": "0230", "hexVariated": "022F", "image": "https://nh-cdn.catalogue.ac/FtrIcon/ToolBagFuroshiki4.png", "filename": "ToolBagFuroshiki4", "color1": "White", "color2": "Green"}, {"name": "Red", "hex": "022E", "hexBase": "0230", "hexVariated": "022E", "image": "https://nh-cdn.catalogue.ac/FtrIcon/ToolBagFuroshiki3.png", "filename": "ToolBagFuroshiki3", "color1": "Red", "color2": "White"}, {"name": "Purple", "hex": "022D", "hexBase": "0230", "hexVariated": "022D", "image": "https://nh-cdn.catalogue.ac/FtrIcon/ToolBagFuroshiki2.png", "filename": "ToolBagFuroshiki2", "color1": "Purple", "color2": "White"}, {"name": "Blue", "hex": "022C", "hexBase": "0230", "hexVariated": "022C", "image": "https://nh-cdn.catalogue.ac/FtrIcon/ToolBagFuroshiki1.png", "filename": "ToolBagFuroshiki1", "color1": "Blue", "color2": "White"}, {"name": "Gold", "hex": "0230", "hexBase": "0230", "hexVariated": "0230", "image": "https://nh-cdn.catalogue.ac/FtrIcon/ToolBagFuroshiki5.png", "filename": "ToolBagFuroshiki5", "color1": "Yellow", "color2": "Yellow"}], "tags": ["Simple", "everyday", "Green", "White", "For sale", "Red", "Purple", "Blue", "Yellow"], "size": "", "catalog": "For sale", "hhaConcept1": "", "hhaConcept2": "", "hhaSeries": "", "hhaSet": "", "diy": "No"}, {"id": "bags-grape-harvest-basket-178", "name": "grape-harvest basket", "rawCategory": "Bags", "category": "Bags", "hexBase": "31FD", "image": "https://nh-cdn.catalogue.ac/ClosetIcon/BagBackpackHarvest0.png", "variants": [{"name": "Default", "hex": "31FD", "hexBase": "31FD", "hexVariated": "31FD", "image": "https://nh-cdn.catalogue.ac/ClosetIcon/BagBackpackHarvest0.png", "filename": "BagBackpackHarvest0", "color1": "Brown", "color2": "Purple"}], "tags": ["Simple", "Active", "everyday", "fairy tale", "outdoorsy", "party", "Brown", "Purple", "Seasonal"], "size": "", "catalog": "Seasonal", "hhaConcept1": "", "hhaConcept2": "", "hhaSeries": "", "hhaSet": "", "diy": "No"}, {"id": "bags-gumdrop-shoulder-bag-179", "name": "gumdrop shoulder bag", "rawCategory": "Bags", "category": "Bags", "hexBase": "2EEC", "image": "https://nh-cdn.catalogue.ac/ClosetIcon/BagShoulderPattern0.png", "variants": [{"name": "Pop", "hex": "1D3E", "hexBase": "2EEC", "hexVariated": "1D3E", "image": "https://nh-cdn.catalogue.ac/ClosetIcon/BagShoulderPattern0.png", "filename": "BagShoulderPattern0", "color1": "Pink", "color2": "Green"}, {"name": "Cool", "hex": "2EEC", "hexBase": "2EEC", "hexVariated": "2EEC", "image": "https://nh-cdn.catalogue.ac/ClosetIcon/BagShoulderPattern1.png", "filename": "BagShoulderPattern1", "color1": "Purple", "color2": "Aqua"}], "tags": ["Simple", "Cute", "everyday", "comfy", "Pink", "Green", "For sale", "Purple", "Aqua"], "size": "", "catalog": "For sale", "hhaConcept1": "", "hhaConcept2": "", "hhaSeries": "", "hhaSet": "", "diy": "No"}, {"id": "bags-hand-knit-pouch-180", "name": "hand-knit pouch", "rawCategory": "Bags", "category": "Bags", "hexBase": "1D3A", "image": "https://nh-cdn.catalogue.ac/ClosetIcon/BagShoulderRace0.png", "variants": [{"name": "Green", "hex": "1D3A", "hexBase": "1D3A", "hexVariated": "1D3A", "image": "https://nh-cdn.catalogue.ac/ClosetIcon/BagShoulderRace0.png", "filename": "BagShoulderRace0", "color1": "Green", "color2": "Green"}, {"name": "Purple", "hex": "2EE4", "hexBase": "1D3A", "hexVariated": "2EE4", "image": "https://nh-cdn.catalogue.ac/ClosetIcon/BagShoulderRace1.png", "filename": "BagShoulderRace1", "color1": "Purple", "color2": "Purple"}], "tags": ["Elegant", "Simple", "vacation", "Green", "For sale", "Purple"], "size": "", "catalog": "For sale", "hhaConcept1": "", "hhaConcept2": "", "hhaSeries": "", "hhaSet": "", "diy": "No"}, {"id": "bags-hard-shell-backpack-181", "name": "hard-shell backpack", "rawCategory": "Bags", "category": "Bags", "hexBase": "1D58", "image": "https://nh-cdn.catalogue.ac/ClosetIcon/BagBackpackHardshell2.png", "variants": [{"name": "Silver", "hex": "2EAA", "hexBase": "1D58", "hexVariated": "2EAA", "image": "https://nh-cdn.catalogue.ac/ClosetIcon/BagBackpackHardshell2.png", "filename": "BagBackpackHardshell2", "color1": "Gray", "color2": "Black"}, {"name": "Red", "hex": "27C8", "hexBase": "1D58", "hexVariated": "27C8", "image": "https://nh-cdn.catalogue.ac/ClosetIcon/BagBackpackHardshell1.png", "filename": "BagBackpackHardshell1", "color1": "Red", "color2": "Black"}, {"name": "Blue", "hex": "1D58", "hexBase": "1D58", "hexVariated": "1D58", "image": "https://nh-cdn.catalogue.ac/ClosetIcon/BagBackpackHardshell0.png", "filename": "BagBackpackHardshell0", "color1": "Blue", "color2": "Black"}], "tags": ["Cool", "Active", "outdoorsy", "work", "Gray", "Black", "For sale", "Red", "Blue"], "size": "", "catalog": "For sale", "hhaConcept1": "", "hhaConcept2": "", "hhaSeries": "", "hhaSet": "", "diy": "No"}, {"id": "bags-hero-s-sword-and-shield-182", "name": "hero's sword and shield", "rawCategory": "Bags", "category": "Bags", "hexBase": "", "image": "https://nh-cdn.catalogue.ac/ClosetIcon/BagBackpackMasterswordHylianshield0.png", "variants": [{"name": "Default", "hex": "", "hexBase": "", "hexVariated": "", "image": "https://nh-cdn.catalogue.ac/ClosetIcon/BagBackpackMasterswordHylianshield0.png", "filename": "BagBackpackMasterswordHylianshield0", "color1": "Blue", "color2": "Gray"}], "tags": ["Simple", "Cool", "fairy tale", "Blue", "Gray", "Not in catalog"], "size": "", "catalog": "Not in catalog", "hhaConcept1": "", "hhaConcept2": "", "hhaSeries": "", "hhaSet": "", "diy": "No"}, {"id": "bags-impish-wings-183", "name": "impish wings", "rawCategory": "Bags", "category": "Bags", "hexBase": "3461", "image": "https://nh-cdn.catalogue.ac/ClosetIcon/BagBackpackHalloween2.png", "variants": [{"name": "White", "hex": "3461", "hexBase": "3461", "hexVariated": "3461", "image": "https://nh-cdn.catalogue.ac/ClosetIcon/BagBackpackHalloween2.png", "filename": "BagBackpackHalloween2", "color1": "White", "color2": "White"}, {"name": "Black", "hex": "3464", "hexBase": "3461", "hexVariated": "3464", "image": "https://nh-cdn.catalogue.ac/ClosetIcon/BagBackpackHalloween5.png", "filename": "BagBackpackHalloween5", "color1": "Black", "color2": "Black"}, {"name": "Red", "hex": "3463", "hexBase": "3461", "hexVariated": "3463", "image": "https://nh-cdn.catalogue.ac/ClosetIcon/BagBackpackHalloween4.png", "filename": "BagBackpackHalloween4", "color1": "Red", "color2": "Red"}, {"name": "Orange", "hex": "32D7", "hexBase": "3461", "hexVariated": "32D7", "image": "https://nh-cdn.catalogue.ac/ClosetIcon/BagBackpackHalloween0.png", "filename": "BagBackpackHalloween0", "color1": "Orange", "color2": "Orange"}, {"name": "Green", "hex": "3462", "hexBase": "3461", "hexVariated": "3462", "image": "https://nh-cdn.catalogue.ac/ClosetIcon/BagBackpackHalloween3.png", "filename": "BagBackpackHalloween3", "color1": "Green", "color2": "Green"}, {"name": "Purple", "hex": "3460", "hexBase": "3461", "hexVariated": "3460", "image": "https://nh-cdn.catalogue.ac/ClosetIcon/BagBackpackHalloween1.png", "filename": "BagBackpackHalloween1", "color1": "Purple", "color2": "Purple"}], "tags": ["Cool", "fairy tale", "goth", "party", "White", "For sale", "Black", "Red", "Orange", "Green", "Purple"], "size": "", "catalog": "For sale", "hhaConcept1": "", "hhaConcept2": "", "hhaSeries": "", "hhaSet": "", "diy": "No"}, {"id": "bags-ink-tank-184", "name": "ink tank", "rawCategory": "Bags", "category": "Bags", "hexBase": "", "image": "https://nh-cdn.catalogue.ac/ClosetIcon/BagBackpackInktank0.png", "variants": [{"name": "Default", "hex": "", "hexBase": "", "hexVariated": "", "image": "https://nh-cdn.catalogue.ac/ClosetIcon/BagBackpackInktank0.png", "filename": "BagBackpackInktank0", "color1": "Yellow", "color2": "Black"}], "tags": ["Active", "Cool", "sporty", "Yellow", "Black", "Not in catalog"], "size": "", "catalog": "Not in catalog", "hhaConcept1": "", "hhaConcept2": "", "hhaSeries": "", "hhaSet": "", "diy": "No"}, {"id": "bags-instrument-case-185", "name": "instrument case", "rawCategory": "Bags", "category": "Bags", "hexBase": "015F", "image": "https://nh-cdn.catalogue.ac/ClosetIcon/BagBackpackMusician0.png", "variants": [{"name": "Black", "hex": "39C0", "hexBase": "015F", "hexVariated": "39C0", "image": "https://nh-cdn.catalogue.ac/ClosetIcon/BagBackpackMusician0.png", "filename": "BagBackpackMusician0", "color1": "Black", "color2": "Black"}, {"name": "White", "hex": "015C", "hexBase": "015F", "hexVariated": "015C", "image": "https://nh-cdn.catalogue.ac/ClosetIcon/BagBackpackMusician1.png", "filename": "BagBackpackMusician1", "color1": "White", "color2": "Black"}, {"name": "Red", "hex": "015E", "hexBase": "015F", "hexVariated": "015E", "image": "https://nh-cdn.catalogue.ac/ClosetIcon/BagBackpackMusician3.png", "filename": "BagBackpackMusician3", "color1": "Red", "color2": "Black"}, {"name": "Pink", "hex": "015F", "hexBase": "015F", "hexVariated": "015F", "image": "https://nh-cdn.catalogue.ac/ClosetIcon/BagBackpackMusician4.png", "filename": "BagBackpackMusician4", "color1": "Pink", "color2": "Black"}, {"name": "Blue", "hex": "015D", "hexBase": "015F", "hexVariated": "015D", "image": "https://nh-cdn.catalogue.ac/ClosetIcon/BagBackpackMusician2.png", "filename": "BagBackpackMusician2", "color1": "Blue", "color2": "Black"}], "tags": ["Simple", "Elegant", "everyday", "theatrical", "Black", "For sale", "White", "Red", "Pink", "Blue"], "size": "", "catalog": "For sale", "hhaConcept1": "", "hhaConcept2": "", "hhaSeries": "", "hhaSet": "", "diy": "No"}, {"id": "bags-jet-pack-186", "name": "jet pack", "rawCategory": "Bags", "category": "Bags", "hexBase": "39E7", "image": "https://nh-cdn.catalogue.ac/ClosetIcon/BagBackpackJet0.png", "variants": [{"name": "Gray", "hex": "39E7", "hexBase": "39E7", "hexVariated": "39E7", "image": "https://nh-cdn.catalogue.ac/ClosetIcon/BagBackpackJet0.png", "filename": "BagBackpackJet0", "color1": "Gray", "color2": "Aqua"}, {"name": "Black", "hex": "0245", "hexBase": "39E7", "hexVariated": "0245", "image": "https://nh-cdn.catalogue.ac/ClosetIcon/BagBackpackJet1.png", "filename": "BagBackpackJet1", "color1": "Black", "color2": "Red"}, {"name": "White", "hex": "024D", "hexBase": "39E7", "hexVariated": "024D", "image": "https://nh-cdn.catalogue.ac/ClosetIcon/BagBackpackJet2.png", "filename": "BagBackpackJet2", "color1": "White", "color2": "Green"}], "tags": ["Cool", "everyday", "work", "Gray", "Aqua", "For sale", "Black", "Red", "White", "Green"], "size": "", "catalog": "For sale", "hhaConcept1": "", "hhaConcept2": "", "hhaSeries": "", "hhaSet": "", "diy": "No"}, {"id": "bags-knapsack-187", "name": "knapsack", "rawCategory": "Bags", "category": "Bags", "hexBase": "1D54", "image": "https://nh-cdn.catalogue.ac/ClosetIcon/BagBackpackKnapsack1.png", "variants": [{"name": "Black", "hex": "2EF3", "hexBase": "1D54", "hexVariated": "2EF3", "image": "https://nh-cdn.catalogue.ac/ClosetIcon/BagBackpackKnapsack1.png", "filename": "BagBackpackKnapsack1", "color1": "Black", "color2": "Black"}, {"name": "Blue", "hex": "1D54", "hexBase": "1D54", "hexVariated": "1D54", "image": "https://nh-cdn.catalogue.ac/ClosetIcon/BagBackpackKnapsack0.png", "filename": "BagBackpackKnapsack0", "color1": "Blue", "color2": "Black"}], "tags": ["Active", "Simple", "everyday", "outdoorsy", "sporty", "Black", "For sale", "Blue"], "size": "", "catalog": "For sale", "hhaConcept1": "", "hhaConcept2": "", "hhaSeries": "", "hhaSet": "", "diy": "No"}, {"id": "bags-knitted-grass-backpack-188", "name": "knitted-grass backpack", "rawCategory": "Bags", "category": "Bags", "hexBase": "1D57", "image": "https://nh-cdn.catalogue.ac/ClosetIcon/BagBackpackGrass0.png", "variants": [{"name": "Default", "hex": "1D57", "hexBase": "1D57", "hexVariated": "1D57", "image": "https://nh-cdn.catalogue.ac/ClosetIcon/BagBackpackGrass0.png", "filename": "BagBackpackGrass0", "color1": "Green", "color2": "Brown"}], "tags": ["Elegant", "Simple", "outdoorsy", "comfy", "vacation", "Green", "Brown", "Not for sale", "DIY"], "size": "", "catalog": "Not for sale", "hhaConcept1": "", "hhaConcept2": "", "hhaSeries": "", "hhaSet": "", "diy": "Yes"}, {"id": "bags-leopard-print-backpack-189", "name": "leopard-print backpack", "rawCategory": "Bags", "category": "Bags", "hexBase": "02AC", "image": "https://nh-cdn.catalogue.ac/ClosetIcon/BagBackpackTownLeopard0.png", "variants": [{"name": "Brown", "hex": "39F7", "hexBase": "02AC", "hexVariated": "39F7", "image": "https://nh-cdn.catalogue.ac/ClosetIcon/BagBackpackTownLeopard0.png", "filename": "BagBackpackTownLeopard0", "color1": "Brown", "color2": "Brown"}, {"name": "Blue", "hex": "02A8", "hexBase": "02AC", "hexVariated": "02A8", "image": "https://nh-cdn.catalogue.ac/ClosetIcon/BagBackpackTownLeopard1.png", "filename": "BagBackpackTownLeopard1", "color1": "Gray", "color2": "Black"}, {"name": "Pink", "hex": "02A9", "hexBase": "02AC", "hexVariated": "02A9", "image": "https://nh-cdn.catalogue.ac/ClosetIcon/BagBackpackTownLeopard2.png", "filename": "BagBackpackTownLeopard2", "color1": "Pink", "color2": "Red"}, {"name": "Yellow", "hex": "02AC", "hexBase": "02AC", "hexVariated": "02AC", "image": "https://nh-cdn.catalogue.ac/ClosetIcon/BagBackpackTownLeopard3.png", "filename": "BagBackpackTownLeopard3", "color1": "Yellow", "color2": "Orange"}], "tags": ["Simple", "Active", "everyday", "Brown", "For sale", "Gray", "Black", "Pink", "Red", "Yellow", "Orange"], "size": "", "catalog": "For sale", "hhaConcept1": "", "hhaConcept2": "", "hhaSeries": "", "hhaSet": "", "diy": "No"}, {"id": "bags-log-pack-190", "name": "log pack", "rawCategory": "Bags", "category": "Bags", "hexBase": "1D4A", "image": "https://nh-cdn.catalogue.ac/ClosetIcon/BagBackpackWood0.png", "variants": [{"name": "Default", "hex": "1D4A", "hexBase": "1D4A", "hexVariated": "1D4A", "image": "https://nh-cdn.catalogue.ac/ClosetIcon/BagBackpackWood0.png", "filename": "BagBackpackWood0", "color1": "Brown", "color2": "Beige"}], "tags": ["Simple", "fairy tale", "outdoorsy", "work", "Brown", "Beige", "Not for sale", "DIY"], "size": "", "catalog": "Not for sale", "hhaConcept1": "", "hhaConcept2": "", "hhaSeries": "", "hhaSet": "", "diy": "Yes"}, {"id": "bags-logo-paper-bag-191", "name": "logo paper bag", "rawCategory": "Bags", "category": "Bags", "hexBase": "0129", "image": "https://nh-cdn.catalogue.ac/FtrIcon/ToolBagPaper0.png", "variants": [{"name": "Green", "hex": "39C6", "hexBase": "0129", "hexVariated": "39C6", "image": "https://nh-cdn.catalogue.ac/FtrIcon/ToolBagPaper0.png", "filename": "ToolBagPaper0", "color1": "Beige", "color2": "Green"}, {"name": "Red", "hex": "0129", "hexBase": "0129", "hexVariated": "0129", "image": "https://nh-cdn.catalogue.ac/FtrIcon/ToolBagPaper1.png", "filename": "ToolBagPaper1", "color1": "Beige", "color2": "Red"}, {"name": "White", "hex": "012B", "hexBase": "0129", "hexVariated": "012B", "image": "https://nh-cdn.catalogue.ac/FtrIcon/ToolBagPaper2.png", "filename": "ToolBagPaper2", "color1": "Beige", "color2": "White"}], "tags": ["Simple", "everyday", "Beige", "Green", "For sale", "Red", "White"], "size": "", "catalog": "For sale", "hhaConcept1": "", "hhaConcept2": "", "hhaSeries": "", "hhaSet": "", "diy": "No"}, {"id": "bags-logo-tote-bag-192", "name": "logo tote bag", "rawCategory": "Bags", "category": "Bags", "hexBase": "3A09", "image": "https://nh-cdn.catalogue.ac/FtrIcon/ToolBagTotelogo0.png", "variants": [{"name": "Gray", "hex": "3A09", "hexBase": "3A09", "hexVariated": "3A09", "image": "https://nh-cdn.catalogue.ac/FtrIcon/ToolBagTotelogo0.png", "filename": "ToolBagTotelogo0", "color1": "Gray", "color2": "White"}, {"name": "Red", "hex": "016D", "hexBase": "3A09", "hexVariated": "016D", "image": "https://nh-cdn.catalogue.ac/FtrIcon/ToolBagTotelogo1.png", "filename": "ToolBagTotelogo1", "color1": "Red", "color2": "White"}, {"name": "Navy blue", "hex": "016E", "hexBase": "3A09", "hexVariated": "016E", "image": "https://nh-cdn.catalogue.ac/FtrIcon/ToolBagTotelogo2.png", "filename": "ToolBagTotelogo2", "color1": "Blue", "color2": "White"}], "tags": ["Simple", "everyday", "Gray", "White", "For sale", "Red", "Blue"], "size": "", "catalog": "For sale", "hhaConcept1": "", "hhaConcept2": "", "hhaSeries": "", "hhaSet": "", "diy": "No"}, {"id": "bags-maple-leaf-pochette-193", "name": "maple-leaf pochette", "rawCategory": "Bags", "category": "Bags", "hexBase": "1D43", "image": "https://nh-cdn.catalogue.ac/ClosetIcon/BagShoulderMaple0.png", "variants": [{"name": "Default", "hex": "1D43", "hexBase": "1D43", "hexVariated": "1D43", "image": "https://nh-cdn.catalogue.ac/ClosetIcon/BagShoulderMaple0.png", "filename": "BagShoulderMaple0", "color1": "Orange", "color2": "Orange"}], "tags": ["Simple", "Cute", "fairy tale", "Orange", "Not for sale", "DIY"], "size": "", "catalog": "Not for sale", "hhaConcept1": "", "hhaConcept2": "", "hhaSeries": "", "hhaSet": "", "diy": "Yes"}, {"id": "bags-messenger-bag-194", "name": "messenger bag", "rawCategory": "Bags", "category": "Bags", "hexBase": "1D2E", "image": "https://nh-cdn.catalogue.ac/ClosetIcon/BagShoulderMessenger2.png", "variants": [{"name": "Black", "hex": "2ECB", "hexBase": "1D2E", "hexVariated": "2ECB", "image": "https://nh-cdn.catalogue.ac/ClosetIcon/BagShoulderMessenger2.png", "filename": "BagShoulderMessenger2", "color1": "Black", "color2": "Black"}, {"name": "Orange", "hex": "2ECA", "hexBase": "1D2E", "hexVariated": "2ECA", "image": "https://nh-cdn.catalogue.ac/ClosetIcon/BagShoulderMessenger1.png", "filename": "BagShoulderMessenger1", "color1": "Orange", "color2": "Black"}, {"name": "Green", "hex": "1D2E", "hexBase": "1D2E", "hexVariated": "1D2E", "image": "https://nh-cdn.catalogue.ac/ClosetIcon/BagShoulderMessenger0.png", "filename": "BagShoulderMessenger0", "color1": "Green", "color2": "Black"}], "tags": ["Simple", "Active", "everyday", "outdoorsy", "sporty", "Black", "For sale", "Orange", "Green"], "size": "", "catalog": "For sale", "hhaConcept1": "", "hhaConcept2": "", "hhaSeries": "", "hhaSet": "", "diy": "No"}, {"id": "bags-mini-pleather-bag-195", "name": "mini pleather bag", "rawCategory": "Bags", "category": "Bags", "hexBase": "2EEF", "image": "https://nh-cdn.catalogue.ac/ClosetIcon/BagBackpackSmall0.png", "variants": [{"name": "White", "hex": "1D50", "hexBase": "2EEF", "hexVariated": "1D50", "image": "https://nh-cdn.catalogue.ac/ClosetIcon/BagBackpackSmall0.png", "filename": "BagBackpackSmall0", "color1": "White", "color2": "White"}, {"name": "Black", "hex": "2EEF", "hexBase": "2EEF", "hexVariated": "2EEF", "image": "https://nh-cdn.catalogue.ac/ClosetIcon/BagBackpackSmall1.png", "filename": "BagBackpackSmall1", "color1": "Black", "color2": "Black"}], "tags": ["Elegant", "everyday", "formal", "party", "White", "For sale", "Black"], "size": "", "catalog": "For sale", "hhaConcept1": "", "hhaConcept2": "", "hhaSeries": "", "hhaSet": "", "diy": "No"}, {"id": "bags-mom-s-knapsack-196", "name": "Mom's knapsack", "rawCategory": "Bags", "category": "Bags", "hexBase": "2F75", "image": "https://nh-cdn.catalogue.ac/ClosetIcon/BagBackpackQuilt6.png", "variants": [{"name": "Forest print", "hex": "2F79", "hexBase": "2F75", "hexVariated": "2F79", "image": "https://nh-cdn.catalogue.ac/ClosetIcon/BagBackpackQuilt6.png", "filename": "BagBackpackQuilt6", "color1": "White", "color2": "Beige"}, {"name": "Flowers", "hex": "2F74", "hexBase": "2F75", "hexVariated": "2F74", "image": "https://nh-cdn.catalogue.ac/ClosetIcon/BagBackpackQuilt1.png", "filename": "BagBackpackQuilt1", "color1": "Gray", "color2": "Beige"}, {"name": "Polka dots", "hex": "2F75", "hexBase": "2F75", "hexVariated": "2F75", "image": "https://nh-cdn.catalogue.ac/ClosetIcon/BagBackpackQuilt2.png", "filename": "BagBackpackQuilt2", "color1": "Pink", "color2": "Beige"}, {"name": "Chick", "hex": "2F7A", "hexBase": "2F75", "hexVariated": "2F7A", "image": "https://nh-cdn.catalogue.ac/ClosetIcon/BagBackpackQuilt7.png", "filename": "BagBackpackQuilt7", "color1": "Orange", "color2": "Beige"}, {"name": "M", "hex": "1D56", "hexBase": "2F75", "hexVariated": "1D56", "image": "https://nh-cdn.catalogue.ac/ClosetIcon/BagBackpackQuilt0.png", "filename": "BagBackpackQuilt0", "color1": "Yellow", "color2": "Beige"}, {"name": "Cherries", "hex": "2F77", "hexBase": "2F75", "hexVariated": "2F77", "image": "https://nh-cdn.catalogue.ac/ClosetIcon/BagBackpackQuilt4.png", "filename": "BagBackpackQuilt4", "color1": "Aqua", "color2": "Beige"}, {"name": "Denim with stripes", "hex": "2F78", "hexBase": "2F75", "hexVariated": "2F78", "image": "https://nh-cdn.catalogue.ac/ClosetIcon/BagBackpackQuilt5.png", "filename": "BagBackpackQuilt5", "color1": "Blue", "color2": "Beige"}, {"name": "Colorful quilt design", "hex": "2F76", "hexBase": "2F75", "hexVariated": "2F76", "image": "https://nh-cdn.catalogue.ac/ClosetIcon/BagBackpackQuilt3.png", "filename": "BagBackpackQuilt3", "color1": "Colorful", "color2": "Beige"}], "tags": ["Cute", "Active", "comfy", "White", "Beige", "Not for sale", "Gray", "Pink", "Orange", "Yellow", "Aqua", "Blue", "Colorful"], "size": "", "catalog": "Not for sale", "hhaConcept1": "", "hhaConcept2": "", "hhaSeries": "", "hhaSet": "", "diy": "No"}, {"id": "bags-nook-inc-knapsack-197", "name": "Nook Inc. knapsack", "rawCategory": "Bags", "category": "Bags", "hexBase": "2621", "image": "https://nh-cdn.catalogue.ac/ClosetIcon/BagBackpackNook0.png", "variants": [{"name": "Default", "hex": "2621", "hexBase": "2621", "hexVariated": "2621", "image": "https://nh-cdn.catalogue.ac/ClosetIcon/BagBackpackNook0.png", "filename": "BagBackpackNook0", "color1": "Brown", "color2": "Yellow"}], "tags": ["Gorgeous", "Active", "everyday", "Brown", "Yellow", "Not for sale"], "size": "", "catalog": "Not for sale", "hhaConcept1": "", "hhaConcept2": "", "hhaSeries": "", "hhaSet": "", "diy": "No"}, {"id": "bags-nook-inc-pochette-198", "name": "Nook Inc. pochette", "rawCategory": "Bags", "category": "Bags", "hexBase": "38CF", "image": "https://nh-cdn.catalogue.ac/ClosetIcon/BagShoulderNook0.png", "variants": [{"name": "Default", "hex": "38CF", "hexBase": "38CF", "hexVariated": "38CF", "image": "https://nh-cdn.catalogue.ac/ClosetIcon/BagShoulderNook0.png", "filename": "BagShoulderNook0", "color1": "Green", "color2": "Green"}], "tags": ["Cute", "Simple", "everyday", "fairy tale", "Green", "Not for sale"], "size": "", "catalog": "Not for sale", "hhaConcept1": "", "hhaConcept2": "", "hhaSeries": "", "hhaSet": "", "diy": "No"}, {"id": "bags-outdoor-backpack-199", "name": "outdoor backpack", "rawCategory": "Bags", "category": "Bags", "hexBase": "2EC1", "image": "https://nh-cdn.catalogue.ac/ClosetIcon/BagBackpackOutdoor1.png", "variants": [{"name": "Orange", "hex": "2EC1", "hexBase": "2EC1", "hexVariated": "2EC1", "image": "https://nh-cdn.catalogue.ac/ClosetIcon/BagBackpackOutdoor1.png", "filename": "BagBackpackOutdoor1", "color1": "Orange", "color2": "Black"}, {"name": "Avocado", "hex": "1D4D", "hexBase": "2EC1", "hexVariated": "1D4D", "image": "https://nh-cdn.catalogue.ac/ClosetIcon/BagBackpackOutdoor0.png", "filename": "BagBackpackOutdoor0", "color1": "Green", "color2": "Black"}, {"name": "Navy blue", "hex": "2EC2", "hexBase": "2EC1", "hexVariated": "2EC2", "image": "https://nh-cdn.catalogue.ac/ClosetIcon/BagBackpackOutdoor2.png", "filename": "BagBackpackOutdoor2", "color1": "Blue", "color2": "Black"}], "tags": ["Active", "Simple", "outdoorsy", "sporty", "Orange", "Black", "For sale", "Green", "Blue"], "size": "", "catalog": "For sale", "hhaConcept1": "", "hhaConcept2": "", "hhaSeries": "", "hhaSet": "", "diy": "No"}, {"id": "bags-panda-backpack-200", "name": "panda backpack", "rawCategory": "Bags", "category": "Bags", "hexBase": "02D0", "image": "https://nh-cdn.catalogue.ac/ClosetIcon/BagBackpackPanda0.png", "variants": [{"name": "Black & white", "hex": "39EE", "hexBase": "02D0", "hexVariated": "39EE", "image": "https://nh-cdn.catalogue.ac/ClosetIcon/BagBackpackPanda0.png", "filename": "BagBackpackPanda0", "color1": "White", "color2": "Black"}, {"name": "Brown", "hex": "02D0", "hexBase": "02D0", "hexVariated": "02D0", "image": "https://nh-cdn.catalogue.ac/ClosetIcon/BagBackpackPanda1.png", "filename": "BagBackpackPanda1", "color1": "Yellow", "color2": "Brown"}], "tags": ["Cute", "everyday", "fairy tale", "White", "Black", "For sale", "Yellow", "Brown"], "size": "", "catalog": "For sale", "hhaConcept1": "", "hhaConcept2": "", "hhaSeries": "", "hhaSet": "", "diy": "No"}, {"id": "bags-pleather-crossbody-bag-201", "name": "pleather crossbody bag", "rawCategory": "Bags", "category": "Bags", "hexBase": "1D3C", "image": "https://nh-cdn.catalogue.ac/ClosetIcon/BagBackpackBodybag1.png", "variants": [{"name": "Black", "hex": "2EE5", "hexBase": "1D3C", "hexVariated": "2EE5", "image": "https://nh-cdn.catalogue.ac/ClosetIcon/BagBackpackBodybag1.png", "filename": "BagBackpackBodybag1", "color1": "Black", "color2": "White"}, {"name": "Navy blue", "hex": "1D3C", "hexBase": "1D3C", "hexVariated": "1D3C", "image": "https://nh-cdn.catalogue.ac/ClosetIcon/BagBackpackBodybag0.png", "filename": "BagBackpackBodybag0", "color1": "Blue", "color2": "Brown"}], "tags": ["Cool", "Simple", "everyday", "work", "Black", "White", "For sale", "Blue", "Brown"], "size": "", "catalog": "For sale", "hhaConcept1": "", "hhaConcept2": "", "hhaSeries": "", "hhaSet": "", "diy": "No"}, {"id": "bags-pleather-fringe-bag-202", "name": "pleather fringe bag", "rawCategory": "Bags", "category": "Bags", "hexBase": "1D39", "image": "https://nh-cdn.catalogue.ac/ClosetIcon/BagShoulderFringe1.png", "variants": [{"name": "White", "hex": "2EEA", "hexBase": "1D39", "hexVariated": "2EEA", "image": "https://nh-cdn.catalogue.ac/ClosetIcon/BagShoulderFringe1.png", "filename": "BagShoulderFringe1", "color1": "White", "color2": "White"}, {"name": "Camel", "hex": "1D39", "hexBase": "1D39", "hexVariated": "1D39", "image": "https://nh-cdn.catalogue.ac/ClosetIcon/BagShoulderFringe0.png", "filename": "BagShoulderFringe0", "color1": "Brown", "color2": "Brown"}], "tags": ["Elegant", "everyday", "formal", "party", "White", "For sale", "Brown"], "size": "", "catalog": "For sale", "hhaConcept1": "", "hhaConcept2": "", "hhaSeries": "", "hhaSet": "", "diy": "No"}, {"id": "bags-pleather-handbag-203", "name": "pleather handbag", "rawCategory": "Bags", "category": "Bags", "hexBase": "013B", "image": "https://nh-cdn.catalogue.ac/FtrIcon/ToolBagLeather0.png", "variants": [{"name": "Red", "hex": "39C5", "hexBase": "013B", "hexVariated": "39C5", "image": "https://nh-cdn.catalogue.ac/FtrIcon/ToolBagLeather0.png", "filename": "ToolBagLeather0", "color1": "Red", "color2": "Red"}, {"name": "Pink", "hex": "0138", "hexBase": "013B", "hexVariated": "0138", "image": "https://nh-cdn.catalogue.ac/FtrIcon/ToolBagLeather3.png", "filename": "ToolBagLeather3", "color1": "Pink", "color2": "Pink"}, {"name": "Orange", "hex": "0136", "hexBase": "013B", "hexVariated": "0136", "image": "https://nh-cdn.catalogue.ac/FtrIcon/ToolBagLeather1.png", "filename": "ToolBagLeather1", "color1": "Orange", "color2": "Orange"}, {"name": "Yellow", "hex": "0139", "hexBase": "013B", "hexVariated": "0139", "image": "https://nh-cdn.catalogue.ac/FtrIcon/ToolBagLeather4.png", "filename": "ToolBagLeather4", "color1": "Yellow", "color2": "Yellow"}, {"name": "Blue", "hex": "0137", "hexBase": "013B", "hexVariated": "0137", "image": "https://nh-cdn.catalogue.ac/FtrIcon/ToolBagLeather2.png", "filename": "ToolBagLeather2", "color1": "Aqua", "color2": "Aqua"}, {"name": "Gray", "hex": "013A", "hexBase": "013B", "hexVariated": "013A", "image": "https://nh-cdn.catalogue.ac/FtrIcon/ToolBagLeather5.png", "filename": "ToolBagLeather5", "color1": "Gray", "color2": "Gray"}, {"name": "Black", "hex": "013B", "hexBase": "013B", "hexVariated": "013B", "image": "https://nh-cdn.catalogue.ac/FtrIcon/ToolBagLeather6.png", "filename": "ToolBagLeather6", "color1": "Black", "color2": "Black"}], "tags": ["Gorgeous", "Elegant", "formal", "party", "work", "Red", "For sale", "Pink", "Orange", "Yellow", "Aqua", "Gray", "Black"], "size": "", "catalog": "For sale", "hhaConcept1": "", "hhaConcept2": "", "hhaSeries": "", "hhaSet": "", "diy": "No"}, {"id": "bags-pleather-shoulder-bag-204", "name": "pleather shoulder bag", "rawCategory": "Bags", "category": "Bags", "hexBase": "2EE9", "image": "https://nh-cdn.catalogue.ac/ClosetIcon/BagShoulderLeather1.png", "variants": [{"name": "Navy blue", "hex": "2EE9", "hexBase": "2EE9", "hexVariated": "2EE9", "image": "https://nh-cdn.catalogue.ac/ClosetIcon/BagShoulderLeather1.png", "filename": "BagShoulderLeather1", "color1": "Blue", "color2": "Blue"}, {"name": "Brown", "hex": "1D34", "hexBase": "2EE9", "hexVariated": "1D34", "image": "https://nh-cdn.catalogue.ac/ClosetIcon/BagShoulderLeather0.png", "filename": "BagShoulderLeather0", "color1": "Brown", "color2": "Brown"}], "tags": ["Elegant", "Simple", "everyday", "formal", "Blue", "For sale", "Brown"], "size": "", "catalog": "For sale", "hhaConcept1": "", "hhaConcept2": "", "hhaSeries": "", "hhaSet": "", "diy": "No"}, {"id": "bags-polka-dot-backpack-205", "name": "polka-dot backpack", "rawCategory": "Bags", "category": "Bags", "hexBase": "02B9", "image": "https://nh-cdn.catalogue.ac/ClosetIcon/BagBackpackTownDot3.png", "variants": [{"name": "Pink", "hex": "02B7", "hexBase": "02B9", "hexVariated": "02B7", "image": "https://nh-cdn.catalogue.ac/ClosetIcon/BagBackpackTownDot3.png", "filename": "BagBackpackTownDot3", "color1": "Red", "color2": "White"}, {"name": "Yellow", "hex": "39FA", "hexBase": "02B9", "hexVariated": "39FA", "image": "https://nh-cdn.catalogue.ac/ClosetIcon/BagBackpackTownDot0.png", "filename": "BagBackpackTownDot0", "color1": "Yellow", "color2": "White"}, {"name": "Lime", "hex": "02B4", "hexBase": "02B9", "hexVariated": "02B4", "image": "https://nh-cdn.catalogue.ac/ClosetIcon/BagBackpackTownDot1.png", "filename": "BagBackpackTownDot1", "color1": "Green", "color2": "White"}, {"name": "Light blue", "hex": "02B6", "hexBase": "02B9", "hexVariated": "02B6", "image": "https://nh-cdn.catalogue.ac/ClosetIcon/BagBackpackTownDot2.png", "filename": "BagBackpackTownDot2", "color1": "Aqua", "color2": "White"}, {"name": "Blue", "hex": "02B9", "hexBase": "02B9", "hexVariated": "02B9", "image": "https://nh-cdn.catalogue.ac/ClosetIcon/BagBackpackTownDot4.png", "filename": "BagBackpackTownDot4", "color1": "Blue", "color2": "White"}], "tags": ["Simple", "Active", "everyday", "Red", "White", "For sale", "Yellow", "Green", "Aqua", "Blue"], "size": "", "catalog": "For sale", "hhaConcept1": "", "hhaConcept2": "", "hhaSeries": "", "hhaSet": "", "diy": "No"}, {"id": "bags-prom-sash-206", "name": "prom sash", "rawCategory": "Bags", "category": "Bags", "hexBase": "3840", "image": "https://nh-cdn.catalogue.ac/ClosetIcon/BagShoulderTasukiprom4.png", "variants": [{"name": "White", "hex": "383E", "hexBase": "3840", "hexVariated": "383E", "image": "https://nh-cdn.catalogue.ac/ClosetIcon/BagShoulderTasukiprom4.png", "filename": "BagShoulderTasukiprom4", "color1": "White", "color2": "Yellow"}, {"name": "Black", "hex": "383F", "hexBase": "3840", "hexVariated": "383F", "image": "https://nh-cdn.catalogue.ac/ClosetIcon/BagShoulderTasukiprom5.png", "filename": "BagShoulderTasukiprom5", "color1": "Black", "color2": "Yellow"}, {"name": "Red", "hex": "37B6", "hexBase": "3840", "hexVariated": "37B6", "image": "https://nh-cdn.catalogue.ac/ClosetIcon/BagShoulderTasukiprom0.png", "filename": "BagShoulderTasukiprom0", "color1": "Red", "color2": "Yellow"}, {"name": "Gold", "hex": "3840", "hexBase": "3840", "hexVariated": "3840", "image": "https://nh-cdn.catalogue.ac/ClosetIcon/BagShoulderTasukiprom6.png", "filename": "BagShoulderTasukiprom6", "color1": "Yellow", "color2": "Black"}, {"name": "Green", "hex": "383C", "hexBase": "3840", "hexVariated": "383C", "image": "https://nh-cdn.catalogue.ac/ClosetIcon/BagShoulderTasukiprom2.png", "filename": "BagShoulderTasukiprom2", "color1": "Green", "color2": "Yellow"}, {"name": "Blue", "hex": "383B", "hexBase": "3840", "hexVariated": "383B", "image": "https://nh-cdn.catalogue.ac/ClosetIcon/BagShoulderTasukiprom1.png", "filename": "BagShoulderTasukiprom1", "color1": "Blue", "color2": "Yellow"}, {"name": "Purple", "hex": "383D", "hexBase": "3840", "hexVariated": "383D", "image": "https://nh-cdn.catalogue.ac/ClosetIcon/BagShoulderTasukiprom3.png", "filename": "BagShoulderTasukiprom3", "color1": "Purple", "color2": "Yellow"}], "tags": ["Gorgeous", "Elegant", "party", "theatrical", "White", "Yellow", "Seasonal", "Black", "Red", "Green", "Blue", "Purple"], "size": "", "catalog": "Seasonal", "hhaConcept1": "", "hhaConcept2": "", "hhaSeries": "", "hhaSet": "", "diy": "No"}, {"id": "bags-python-print-shoulder-bag-207", "name": "python-print shoulder bag", "rawCategory": "Bags", "category": "Bags", "hexBase": "02D3", "image": "https://nh-cdn.catalogue.ac/ClosetIcon/BagShoulderSquarePython0.png", "variants": [{"name": "Brown", "hex": "3A2E", "hexBase": "02D3", "hexVariated": "3A2E", "image": "https://nh-cdn.catalogue.ac/ClosetIcon/BagShoulderSquarePython0.png", "filename": "BagShoulderSquarePython0", "color1": "Brown", "color2": "Black"}, {"name": "Gray", "hex": "02D3", "hexBase": "02D3", "hexVariated": "02D3", "image": "https://nh-cdn.catalogue.ac/ClosetIcon/BagShoulderSquarePython1.png", "filename": "BagShoulderSquarePython1", "color1": "Gray", "color2": "Black"}], "tags": ["Simple", "everyday", "Brown", "Black", "For sale", "Gray"], "size": "", "catalog": "For sale", "hhaConcept1": "", "hhaConcept2": "", "hhaSeries": "", "hhaSet": "", "diy": "No"}, {"id": "bags-randoseru-208", "name": "randoseru", "rawCategory": "Bags", "category": "Bags", "hexBase": "0103", "image": "https://nh-cdn.catalogue.ac/ClosetIcon/BagBackpackRandsel0.png", "variants": [{"name": "Red", "hex": "381E", "hexBase": "0103", "hexVariated": "381E", "image": "https://nh-cdn.catalogue.ac/ClosetIcon/BagBackpackRandsel0.png", "filename": "BagBackpackRandsel0", "color1": "Red", "color2": "Red"}, {"name": "Black", "hex": "00FE", "hexBase": "0103", "hexVariated": "00FE", "image": "https://nh-cdn.catalogue.ac/ClosetIcon/BagBackpackRandsel1.png", "filename": "BagBackpackRandsel1", "color1": "Black", "color2": "Black"}, {"name": "Pink", "hex": "0103", "hexBase": "0103", "hexVariated": "0103", "image": "https://nh-cdn.catalogue.ac/ClosetIcon/BagBackpackRandsel6.png", "filename": "BagBackpackRandsel6", "color1": "Pink", "color2": "Pink"}, {"name": "Green", "hex": "0100", "hexBase": "0103", "hexVariated": "0100", "image": "https://nh-cdn.catalogue.ac/ClosetIcon/BagBackpackRandsel3.png", "filename": "BagBackpackRandsel3", "color1": "Green", "color2": "Green"}, {"name": "Light blue", "hex": "0102", "hexBase": "0103", "hexVariated": "0102", "image": "https://nh-cdn.catalogue.ac/ClosetIcon/BagBackpackRandsel5.png", "filename": "BagBackpackRandsel5", "color1": "Aqua", "color2": "Aqua"}, {"name": "Blue", "hex": "0101", "hexBase": "0103", "hexVariated": "0101", "image": "https://nh-cdn.catalogue.ac/ClosetIcon/BagBackpackRandsel4.png", "filename": "BagBackpackRandsel4", "color1": "Blue", "color2": "Blue"}, {"name": "Purple", "hex": "0104", "hexBase": "0103", "hexVariated": "0104", "image": "https://nh-cdn.catalogue.ac/ClosetIcon/BagBackpackRandsel7.png", "filename": "BagBackpackRandsel7", "color1": "Purple", "color2": "Purple"}, {"name": "Brown", "hex": "00FF", "hexBase": "0103", "hexVariated": "00FF", "image": "https://nh-cdn.catalogue.ac/ClosetIcon/BagBackpackRandsel2.png", "filename": "BagBackpackRandsel2", "color1": "Brown", "color2": "Brown"}], "tags": ["Simple", "everyday", "formal", "Red", "For sale", "Black", "Pink", "Green", "Aqua", "Blue", "Purple", "Brown"], "size": "", "catalog": "For sale", "hhaConcept1": "", "hhaConcept2": "", "hhaSeries": "", "hhaSet": "", "diy": "No"}, {"id": "bags-retro-sports-bag-209", "name": "retro sports bag", "rawCategory": "Bags", "category": "Bags", "hexBase": "2EE8", "image": "https://nh-cdn.catalogue.ac/ClosetIcon/BagShoulderSports1.png", "variants": [{"name": "Red", "hex": "2EE7", "hexBase": "2EE8", "hexVariated": "2EE7", "image": "https://nh-cdn.catalogue.ac/ClosetIcon/BagShoulderSports1.png", "filename": "BagShoulderSports1", "color1": "White", "color2": "Red"}, {"name": "Blue", "hex": "1C86", "hexBase": "2EE8", "hexVariated": "1C86", "image": "https://nh-cdn.catalogue.ac/ClosetIcon/BagShoulderSports0.png", "filename": "BagShoulderSports0", "color1": "White", "color2": "Blue"}, {"name": "Black", "hex": "2EE8", "hexBase": "2EE8", "hexVariated": "2EE8", "image": "https://nh-cdn.catalogue.ac/ClosetIcon/BagShoulderSports2.png", "filename": "BagShoulderSports2", "color1": "Black", "color2": "Yellow"}], "tags": ["Active", "outdoorsy", "sporty", "White", "Red", "For sale", "Blue", "Black", "Yellow"], "size": "", "catalog": "For sale", "hhaConcept1": "", "hhaConcept2": "", "hhaSeries": "", "hhaSet": "", "diy": "No"}, {"id": "bags-sacoche-bag-210", "name": "sacoche bag", "rawCategory": "Bags", "category": "Bags", "hexBase": "1C88", "image": "https://nh-cdn.catalogue.ac/ClosetIcon/BagShoulderSacosh2.png", "variants": [{"name": "Black", "hex": "2EC7", "hexBase": "1C88", "hexVariated": "2EC7", "image": "https://nh-cdn.catalogue.ac/ClosetIcon/BagShoulderSacosh2.png", "filename": "BagShoulderSacosh2", "color1": "Black", "color2": "White"}, {"name": "Red", "hex": "2EC6", "hexBase": "1C88", "hexVariated": "2EC6", "image": "https://nh-cdn.catalogue.ac/ClosetIcon/BagShoulderSacosh1.png", "filename": "BagShoulderSacosh1", "color1": "Red", "color2": "Yellow"}, {"name": "Blue", "hex": "1C88", "hexBase": "1C88", "hexVariated": "1C88", "image": "https://nh-cdn.catalogue.ac/ClosetIcon/BagShoulderSacosh0.png", "filename": "BagShoulderSacosh0", "color1": "Blue", "color2": "Green"}], "tags": ["Active", "outdoorsy", "sporty", "Black", "White", "For sale", "Red", "Yellow", "Blue", "Green"], "size": "", "catalog": "For sale", "hhaConcept1": "", "hhaConcept2": "", "hhaSeries": "", "hhaSet": "", "diy": "No"}, {"id": "bags-satchel-211", "name": "satchel", "rawCategory": "Bags", "category": "Bags", "hexBase": "0275", "image": "https://nh-cdn.catalogue.ac/ClosetIcon/BagBackpackStudent1.png", "variants": [{"name": "Black", "hex": "0251", "hexBase": "0275", "hexVariated": "0251", "image": "https://nh-cdn.catalogue.ac/ClosetIcon/BagBackpackStudent1.png", "filename": "BagBackpackStudent1", "color1": "Black", "color2": "Gray"}, {"name": "Red", "hex": "028F", "hexBase": "0275", "hexVariated": "028F", "image": "https://nh-cdn.catalogue.ac/ClosetIcon/BagBackpackStudent4.png", "filename": "BagBackpackStudent4", "color1": "Red", "color2": "Yellow"}, {"name": "Blue", "hex": "028E", "hexBase": "0275", "hexVariated": "028E", "image": "https://nh-cdn.catalogue.ac/ClosetIcon/BagBackpackStudent3.png", "filename": "BagBackpackStudent3", "color1": "Blue", "color2": "Brown"}, {"name": "Brown", "hex": "39E8", "hexBase": "0275", "hexVariated": "39E8", "image": "https://nh-cdn.catalogue.ac/ClosetIcon/BagBackpackStudent0.png", "filename": "BagBackpackStudent0", "color1": "Brown", "color2": "Beige"}, {"name": "Camel", "hex": "0275", "hexBase": "0275", "hexVariated": "0275", "image": "https://nh-cdn.catalogue.ac/ClosetIcon/BagBackpackStudent2.png", "filename": "BagBackpackStudent2", "color1": "Beige", "color2": "Brown"}], "tags": ["Simple", "Cool", "formal", "work", "Black", "Gray", "For sale", "Red", "Yellow", "Blue", "Brown", "Beige"], "size": "", "catalog": "For sale", "hhaConcept1": "", "hhaConcept2": "", "hhaSeries": "", "hhaSet": "", "diy": "No"}, {"id": "bags-schoolbag-212", "name": "schoolbag", "rawCategory": "Bags", "category": "Bags", "hexBase": "381F", "image": "https://nh-cdn.catalogue.ac/ClosetIcon/BagBackpackSchoolbag0.png", "variants": [{"name": "Blue", "hex": "381F", "hexBase": "381F", "hexVariated": "381F", "image": "https://nh-cdn.catalogue.ac/ClosetIcon/BagBackpackSchoolbag0.png", "filename": "BagBackpackSchoolbag0", "color1": "Blue", "color2": "White"}, {"name": "Gray", "hex": "0107", "hexBase": "381F", "hexVariated": "0107", "image": "https://nh-cdn.catalogue.ac/ClosetIcon/BagBackpackSchoolbag3.png", "filename": "BagBackpackSchoolbag3", "color1": "Gray", "color2": "White"}, {"name": "Black", "hex": "0106", "hexBase": "381F", "hexVariated": "0106", "image": "https://nh-cdn.catalogue.ac/ClosetIcon/BagBackpackSchoolbag2.png", "filename": "BagBackpackSchoolbag2", "color1": "Black", "color2": "White"}, {"name": "Green", "hex": "0109", "hexBase": "381F", "hexVariated": "0109", "image": "https://nh-cdn.catalogue.ac/ClosetIcon/BagBackpackSchoolbag5.png", "filename": "BagBackpackSchoolbag5", "color1": "Green", "color2": "White"}, {"name": "Navy blue", "hex": "0105", "hexBase": "381F", "hexVariated": "0105", "image": "https://nh-cdn.catalogue.ac/ClosetIcon/BagBackpackSchoolbag1.png", "filename": "BagBackpackSchoolbag1", "color1": "Blue", "color2": "White"}, {"name": "Brown", "hex": "0108", "hexBase": "381F", "hexVariated": "0108", "image": "https://nh-cdn.catalogue.ac/ClosetIcon/BagBackpackSchoolbag4.png", "filename": "BagBackpackSchoolbag4", "color1": "Brown", "color2": "White"}], "tags": ["Simple", "everyday", "formal", "Blue", "White", "For sale", "Gray", "Black", "Green", "Brown"], "size": "", "catalog": "For sale", "hhaConcept1": "", "hhaConcept2": "", "hhaSeries": "", "hhaSet": "", "diy": "No"}, {"id": "bags-shellfish-pochette-213", "name": "shellfish pochette", "rawCategory": "Bags", "category": "Bags", "hexBase": "1D46", "image": "https://nh-cdn.catalogue.ac/ClosetIcon/BagShoulderShell0.png", "variants": [{"name": "Default", "hex": "1D46", "hexBase": "1D46", "hexVariated": "1D46", "image": "https://nh-cdn.catalogue.ac/ClosetIcon/BagShoulderShell0.png", "filename": "BagShoulderShell0", "color1": "White", "color2": "White"}], "tags": ["Cute", "Elegant", "fairy tale", "vacation", "White", "Not for sale", "DIY"], "size": "", "catalog": "Not for sale", "hhaConcept1": "", "hhaConcept2": "", "hhaSeries": "", "hhaSet": "", "diy": "Yes"}, {"id": "bags-simple-backpack-214", "name": "simple backpack", "rawCategory": "Bags", "category": "Bags", "hexBase": "02BB", "image": "https://nh-cdn.catalogue.ac/ClosetIcon/BagBackpackTownSimple0.png", "variants": [{"name": "Camel", "hex": "39FB", "hexBase": "02BB", "hexVariated": "39FB", "image": "https://nh-cdn.catalogue.ac/ClosetIcon/BagBackpackTownSimple0.png", "filename": "BagBackpackTownSimple0", "color1": "Brown", "color2": "Brown"}, {"name": "Gray", "hex": "02BB", "hexBase": "02BB", "hexVariated": "02BB", "image": "https://nh-cdn.catalogue.ac/ClosetIcon/BagBackpackTownSimple1.png", "filename": "BagBackpackTownSimple1", "color1": "Gray", "color2": "Gray"}, {"name": "Black", "hex": "02D1", "hexBase": "02BB", "hexVariated": "02D1", "image": "https://nh-cdn.catalogue.ac/ClosetIcon/BagBackpackTownSimple2.png", "filename": "BagBackpackTownSimple2", "color1": "Black", "color2": "Black"}], "tags": ["Simple", "Active", "everyday", "Brown", "For sale", "Gray", "Black"], "size": "", "catalog": "For sale", "hhaConcept1": "", "hhaConcept2": "", "hhaSeries": "", "hhaSet": "", "diy": "No"}, {"id": "bags-simple-tote-bag-215", "name": "simple tote bag", "rawCategory": "Bags", "category": "Bags", "hexBase": "39C3", "image": "https://nh-cdn.catalogue.ac/FtrIcon/ToolBagTote0.png", "variants": [{"name": "Red", "hex": "39C3", "hexBase": "39C3", "hexVariated": "39C3", "image": "https://nh-cdn.catalogue.ac/FtrIcon/ToolBagTote0.png", "filename": "ToolBagTote0", "color1": "White", "color2": "Red"}, {"name": "Yellow", "hex": "0166", "hexBase": "39C3", "hexVariated": "0166", "image": "https://nh-cdn.catalogue.ac/FtrIcon/ToolBagTote2.png", "filename": "ToolBagTote2", "color1": "White", "color2": "Yellow"}, {"name": "Green", "hex": "0167", "hexBase": "39C3", "hexVariated": "0167", "image": "https://nh-cdn.catalogue.ac/FtrIcon/ToolBagTote3.png", "filename": "ToolBagTote3", "color1": "White", "color2": "Green"}, {"name": "Blue", "hex": "0165", "hexBase": "39C3", "hexVariated": "0165", "image": "https://nh-cdn.catalogue.ac/FtrIcon/ToolBagTote1.png", "filename": "ToolBagTote1", "color1": "White", "color2": "Blue"}, {"name": "Black & white", "hex": "0169", "hexBase": "39C3", "hexVariated": "0169", "image": "https://nh-cdn.catalogue.ac/FtrIcon/ToolBagTote5.png", "filename": "ToolBagTote5", "color1": "Black", "color2": "White"}, {"name": "Beige", "hex": "0168", "hexBase": "39C3", "hexVariated": "0168", "image": "https://nh-cdn.catalogue.ac/FtrIcon/ToolBagTote4.png", "filename": "ToolBagTote4", "color1": "Beige", "color2": "White"}], "tags": ["Simple", "everyday", "White", "Red", "For sale", "Yellow", "Green", "Blue", "Black", "Beige"], "size": "", "catalog": "For sale", "hhaConcept1": "", "hhaConcept2": "", "hhaSeries": "", "hhaSet": "", "diy": "No"}, {"id": "bags-snowflake-pochette-216", "name": "snowflake pochette", "rawCategory": "Bags", "category": "Bags", "hexBase": "1D45", "image": "https://nh-cdn.catalogue.ac/ClosetIcon/BagShoulderSnow0.png", "variants": [{"name": "Default", "hex": "1D45", "hexBase": "1D45", "hexVariated": "1D45", "image": "https://nh-cdn.catalogue.ac/ClosetIcon/BagShoulderSnow0.png", "filename": "BagShoulderSnow0", "color1": "Aqua", "color2": "White"}], "tags": ["Elegant", "Cool", "fairy tale", "party", "vacation", "Aqua", "White", "Not for sale", "DIY"], "size": "", "catalog": "Not for sale", "hhaConcept1": "", "hhaConcept2": "", "hhaSeries": "", "hhaSet": "", "diy": "Yes"}, {"id": "bags-spacey-backpack-217", "name": "spacey backpack", "rawCategory": "Bags", "category": "Bags", "hexBase": "39F8", "image": "https://nh-cdn.catalogue.ac/ClosetIcon/BagBackpackTownSpace2.png", "variants": [{"name": "Pink", "hex": "02AF", "hexBase": "39F8", "hexVariated": "02AF", "image": "https://nh-cdn.catalogue.ac/ClosetIcon/BagBackpackTownSpace2.png", "filename": "BagBackpackTownSpace2", "color1": "Pink", "color2": "Purple"}, {"name": "Purple", "hex": "02AE", "hexBase": "39F8", "hexVariated": "02AE", "image": "https://nh-cdn.catalogue.ac/ClosetIcon/BagBackpackTownSpace1.png", "filename": "BagBackpackTownSpace1", "color1": "Green", "color2": "Purple"}, {"name": "Blue", "hex": "39F8", "hexBase": "39F8", "hexVariated": "39F8", "image": "https://nh-cdn.catalogue.ac/ClosetIcon/BagBackpackTownSpace0.png", "filename": "BagBackpackTownSpace0", "color1": "Blue", "color2": "Purple"}], "tags": ["Simple", "Active", "everyday", "Pink", "Purple", "For sale", "Green", "Blue"], "size": "", "catalog": "For sale", "hhaConcept1": "", "hhaConcept2": "", "hhaSeries": "", "hhaSet": "", "diy": "No"}, {"id": "bags-square-backpack-218", "name": "square backpack", "rawCategory": "Bags", "category": "Bags", "hexBase": "2EC0", "image": "https://nh-cdn.catalogue.ac/ClosetIcon/BagBackpackSquare1.png", "variants": [{"name": "Pink", "hex": "2EBF", "hexBase": "2EC0", "hexVariated": "2EBF", "image": "https://nh-cdn.catalogue.ac/ClosetIcon/BagBackpackSquare1.png", "filename": "BagBackpackSquare1", "color1": "Pink", "color2": "Black"}, {"name": "Yellow", "hex": "1D4C", "hexBase": "2EC0", "hexVariated": "1D4C", "image": "https://nh-cdn.catalogue.ac/ClosetIcon/BagBackpackSquare0.png", "filename": "BagBackpackSquare0", "color1": "Yellow", "color2": "Black"}, {"name": "Green", "hex": "2EC0", "hexBase": "2EC0", "hexVariated": "2EC0", "image": "https://nh-cdn.catalogue.ac/ClosetIcon/BagBackpackSquare2.png", "filename": "BagBackpackSquare2", "color1": "Green", "color2": "Black"}], "tags": ["Active", "everyday", "outdoorsy", "sporty", "Pink", "Black", "For sale", "Yellow", "Green"], "size": "", "catalog": "For sale", "hhaConcept1": "", "hhaConcept2": "", "hhaSeries": "", "hhaSet": "", "diy": "No"}, {"id": "bags-square-shoulder-bag-219", "name": "square shoulder bag", "rawCategory": "Bags", "category": "Bags", "hexBase": "39E6", "image": "https://nh-cdn.catalogue.ac/ClosetIcon/BagShoulderSquare0.png", "variants": [{"name": "Black", "hex": "39E6", "hexBase": "39E6", "hexVariated": "39E6", "image": "https://nh-cdn.catalogue.ac/ClosetIcon/BagShoulderSquare0.png", "filename": "BagShoulderSquare0", "color1": "Black", "color2": "Black"}, {"name": "Beige", "hex": "0244", "hexBase": "39E6", "hexVariated": "0244", "image": "https://nh-cdn.catalogue.ac/ClosetIcon/BagShoulderSquare1.png", "filename": "BagShoulderSquare1", "color1": "Beige", "color2": "Beige"}], "tags": ["Simple", "everyday", "Black", "For sale", "Beige"], "size": "", "catalog": "For sale", "hhaConcept1": "", "hhaConcept2": "", "hhaSeries": "", "hhaSet": "", "diy": "No"}, {"id": "bags-star-pochette-220", "name": "star pochette", "rawCategory": "Bags", "category": "Bags", "hexBase": "1D41", "image": "https://nh-cdn.catalogue.ac/ClosetIcon/BagShoulderStar0.png", "variants": [{"name": "Default", "hex": "1D41", "hexBase": "1D41", "hexVariated": "1D41", "image": "https://nh-cdn.catalogue.ac/ClosetIcon/BagShoulderStar0.png", "filename": "BagShoulderStar0", "color1": "Yellow", "color2": "Yellow"}], "tags": ["Cute", "Gorgeous", "fairy tale", "party", "vacation", "Yellow", "Not for sale", "DIY"], "size": "", "catalog": "Not for sale", "hhaConcept1": "", "hhaConcept2": "", "hhaSeries": "", "hhaSet": "", "diy": "Yes"}, {"id": "bags-straw-pochette-221", "name": "straw pochette", "rawCategory": "Bags", "category": "Bags", "hexBase": "1D40", "image": "https://nh-cdn.catalogue.ac/ClosetIcon/BagShoulderRattan0.png", "variants": [{"name": "Default", "hex": "1D40", "hexBase": "1D40", "hexVariated": "1D40", "image": "https://nh-cdn.catalogue.ac/ClosetIcon/BagShoulderRattan0.png", "filename": "BagShoulderRattan0", "color1": "Brown", "color2": "Brown"}], "tags": ["Simple", "Elegant", "comfy", "vacation", "Brown", "For sale"], "size": "", "catalog": "For sale", "hhaConcept1": "", "hhaConcept2": "", "hhaSeries": "", "hhaSet": "", "diy": "No"}, {"id": "bags-striped-basket-bag-222", "name": "striped basket bag", "rawCategory": "Bags", "category": "Bags", "hexBase": "3A07", "image": "https://nh-cdn.catalogue.ac/FtrIcon/ToolBagBasketborder0.png", "variants": [{"name": "Brown", "hex": "3A07", "hexBase": "3A07", "hexVariated": "3A07", "image": "https://nh-cdn.catalogue.ac/FtrIcon/ToolBagBasketborder0.png", "filename": "ToolBagBasketborder0", "color1": "Beige", "color2": "Brown"}, {"name": "Black & white", "hex": "016A", "hexBase": "3A07", "hexVariated": "016A", "image": "https://nh-cdn.catalogue.ac/FtrIcon/ToolBagBasketborder1.png", "filename": "ToolBagBasketborder1", "color1": "Black", "color2": "White"}], "tags": ["Simple", "Cute", "everyday", "fairy tale", "vacation", "Beige", "Brown", "For sale", "Black", "White"], "size": "", "catalog": "For sale", "hhaConcept1": "", "hhaConcept2": "", "hhaSeries": "", "hhaSet": "", "diy": "No"}, {"id": "bags-studded-backpack-223", "name": "studded backpack", "rawCategory": "Bags", "category": "Bags", "hexBase": "2EE6", "image": "https://nh-cdn.catalogue.ac/ClosetIcon/BagBackpackStuds1.png", "variants": [{"name": "White", "hex": "2EE6", "hexBase": "2EE6", "hexVariated": "2EE6", "image": "https://nh-cdn.catalogue.ac/ClosetIcon/BagBackpackStuds1.png", "filename": "BagBackpackStuds1", "color1": "White", "color2": "Gray"}, {"name": "Black", "hex": "1D4F", "hexBase": "2EE6", "hexVariated": "1D4F", "image": "https://nh-cdn.catalogue.ac/ClosetIcon/BagBackpackStuds0.png", "filename": "BagBackpackStuds0", "color1": "Black", "color2": "Yellow"}], "tags": ["Cool", "Cute", "everyday", "goth", "White", "Gray", "For sale", "Black", "Yellow"], "size": "", "catalog": "For sale", "hhaConcept1": "", "hhaConcept2": "", "hhaSeries": "", "hhaSet": "", "diy": "No"}, {"id": "bags-sword-in-scabbard-224", "name": "sword in scabbard", "rawCategory": "Bags", "category": "Bags", "hexBase": "02C9", "image": "https://nh-cdn.catalogue.ac/ClosetIcon/BagShoulderSword0.png", "variants": [{"name": "Red", "hex": "39C1", "hexBase": "02C9", "hexVariated": "39C1", "image": "https://nh-cdn.catalogue.ac/ClosetIcon/BagShoulderSword0.png", "filename": "BagShoulderSword0", "color1": "Red", "color2": "Yellow"}, {"name": "Blue", "hex": "02C7", "hexBase": "02C9", "hexVariated": "02C7", "image": "https://nh-cdn.catalogue.ac/ClosetIcon/BagShoulderSword1.png", "filename": "BagShoulderSword1", "color1": "Blue", "color2": "Gray"}, {"name": "Black", "hex": "02C9", "hexBase": "02C9", "hexVariated": "02C9", "image": "https://nh-cdn.catalogue.ac/ClosetIcon/BagShoulderSword2.png", "filename": "BagShoulderSword2", "color1": "Black", "color2": "Yellow"}], "tags": ["Cool", "Active", "fairy tale", "theatrical", "Red", "Yellow", "For sale", "Blue", "Gray", "Black"], "size": "", "catalog": "For sale", "hhaConcept1": "", "hhaConcept2": "", "hhaSeries": "", "hhaSet": "", "diy": "No"}, {"id": "bags-tackle-bag-225", "name": "tackle bag", "rawCategory": "Bags", "category": "Bags", "hexBase": "1D36", "image": "https://nh-cdn.catalogue.ac/ClosetIcon/BagShoulderFishing0.png", "variants": [{"name": "Default", "hex": "1D36", "hexBase": "1D36", "hexVariated": "1D36", "image": "https://nh-cdn.catalogue.ac/ClosetIcon/BagShoulderFishing0.png", "filename": "BagShoulderFishing0", "color1": "Blue", "color2": "Orange"}], "tags": ["Active", "outdoorsy", "sporty", "work", "Blue", "Orange", "Not for sale"], "size": "", "catalog": "Not for sale", "hhaConcept1": "", "hhaConcept2": "", "hhaSeries": "", "hhaSet": "", "diy": "No"}, {"id": "bags-tiny-flower-print-tote-bag-226", "name": "tiny-flower-print tote bag", "rawCategory": "Bags", "category": "Bags", "hexBase": "3A08", "image": "https://nh-cdn.catalogue.ac/FtrIcon/ToolBagToteflower0.png", "variants": [{"name": "Pink", "hex": "3A08", "hexBase": "3A08", "hexVariated": "3A08", "image": "https://nh-cdn.catalogue.ac/FtrIcon/ToolBagToteflower0.png", "filename": "ToolBagToteflower0", "color1": "White", "color2": "Pink"}, {"name": "Yellow", "hex": "016C", "hexBase": "3A08", "hexVariated": "016C", "image": "https://nh-cdn.catalogue.ac/FtrIcon/ToolBagToteflower2.png", "filename": "ToolBagToteflower2", "color1": "White", "color2": "Yellow"}, {"name": "Light blue", "hex": "016B", "hexBase": "3A08", "hexVariated": "016B", "image": "https://nh-cdn.catalogue.ac/FtrIcon/ToolBagToteflower1.png", "filename": "ToolBagToteflower1", "color1": "White", "color2": "Aqua"}], "tags": ["Simple", "Cute", "everyday", "fairy tale", "outdoorsy", "White", "Pink", "For sale", "Yellow", "Aqua"], "size": "", "catalog": "For sale", "hhaConcept1": "", "hhaConcept2": "", "hhaSeries": "", "hhaSet": "", "diy": "No"}, {"id": "bags-tool-bag-227", "name": "tool bag", "rawCategory": "Bags", "category": "Bags", "hexBase": "1D49", "image": "https://nh-cdn.catalogue.ac/ClosetIcon/BagShoulderTool0.png", "variants": [{"name": "Default", "hex": "1D49", "hexBase": "1D49", "hexVariated": "1D49", "image": "https://nh-cdn.catalogue.ac/ClosetIcon/BagShoulderTool0.png", "filename": "BagShoulderTool0", "color1": "Black", "color2": "Yellow"}], "tags": ["Active", "outdoorsy", "work", "Black", "Yellow", "For sale"], "size": "", "catalog": "For sale", "hhaConcept1": "", "hhaConcept2": "", "hhaSeries": "", "hhaSet": "", "diy": "No"}, {"id": "bags-town-backpack-228", "name": "town backpack", "rawCategory": "Bags", "category": "Bags", "hexBase": "2EA9", "image": "https://nh-cdn.catalogue.ac/ClosetIcon/BagBackpackTown3.png", "variants": [{"name": "Red", "hex": "2EA9", "hexBase": "2EA9", "hexVariated": "2EA9", "image": "https://nh-cdn.catalogue.ac/ClosetIcon/BagBackpackTown3.png", "filename": "BagBackpackTown3", "color1": "Red", "color2": "Red"}, {"name": "Orange", "hex": "1AB7", "hexBase": "2EA9", "hexVariated": "1AB7", "image": "https://nh-cdn.catalogue.ac/ClosetIcon/BagBackpackTown1.png", "filename": "BagBackpackTown1", "color1": "Orange", "color2": "Orange"}, {"name": "Green", "hex": "1AB6", "hexBase": "2EA9", "hexVariated": "1AB6", "image": "https://nh-cdn.catalogue.ac/ClosetIcon/BagBackpackTown0.png", "filename": "BagBackpackTown0", "color1": "Green", "color2": "Green"}, {"name": "Blue", "hex": "2EA8", "hexBase": "2EA9", "hexVariated": "2EA8", "image": "https://nh-cdn.catalogue.ac/ClosetIcon/BagBackpackTown2.png", "filename": "BagBackpackTown2", "color1": "Blue", "color2": "Blue"}], "tags": ["Active", "Simple", "everyday", "outdoorsy", "Red", "For sale", "Orange", "Green", "Blue"], "size": "", "catalog": "For sale", "hhaConcept1": "", "hhaConcept2": "", "hhaSeries": "", "hhaSet": "", "diy": "No"}, {"id": "bags-travel-pouch-229", "name": "travel pouch", "rawCategory": "Bags", "category": "Bags", "hexBase": "2EE2", "image": "https://nh-cdn.catalogue.ac/ClosetIcon/BagShoulderTravel0.png", "variants": [{"name": "Pink", "hex": "09F6", "hexBase": "2EE2", "hexVariated": "09F6", "image": "https://nh-cdn.catalogue.ac/ClosetIcon/BagShoulderTravel0.png", "filename": "BagShoulderTravel0", "color1": "Pink", "color2": "Black"}, {"name": "Green", "hex": "2EE0", "hexBase": "2EE2", "hexVariated": "2EE0", "image": "https://nh-cdn.catalogue.ac/ClosetIcon/BagShoulderTravel1.png", "filename": "BagShoulderTravel1", "color1": "Green", "color2": "Black"}, {"name": "Light blue", "hex": "2EE1", "hexBase": "2EE2", "hexVariated": "2EE1", "image": "https://nh-cdn.catalogue.ac/ClosetIcon/BagShoulderTravel2.png", "filename": "BagShoulderTravel2", "color1": "Aqua", "color2": "Black"}, {"name": "Purple", "hex": "2EE2", "hexBase": "2EE2", "hexVariated": "2EE2", "image": "https://nh-cdn.catalogue.ac/ClosetIcon/BagShoulderTravel3.png", "filename": "BagShoulderTravel3", "color1": "Purple", "color2": "Black"}], "tags": ["Active", "Simple", "everyday", "outdoorsy", "Pink", "Black", "For sale", "Green", "Aqua", "Purple"], "size": "", "catalog": "For sale", "hhaConcept1": "", "hhaConcept2": "", "hhaSeries": "", "hhaSet": "", "diy": "No"}, {"id": "bags-traveler-s-backpack-230", "name": "traveler's backpack", "rawCategory": "Bags", "category": "Bags", "hexBase": "1D4B", "image": "https://nh-cdn.catalogue.ac/ClosetIcon/BagBackpackJourney0.png", "variants": [{"name": "Orange", "hex": "1D4B", "hexBase": "1D4B", "hexVariated": "1D4B", "image": "https://nh-cdn.catalogue.ac/ClosetIcon/BagBackpackJourney0.png", "filename": "BagBackpackJourney0", "color1": "Orange", "color2": "Beige"}, {"name": "Blue", "hex": "2EBD", "hexBase": "1D4B", "hexVariated": "2EBD", "image": "https://nh-cdn.catalogue.ac/ClosetIcon/BagBackpackJourney1.png", "filename": "BagBackpackJourney1", "color1": "Blue", "color2": "Beige"}, {"name": "Brown", "hex": "2EBE", "hexBase": "1D4B", "hexVariated": "2EBE", "image": "https://nh-cdn.catalogue.ac/ClosetIcon/BagBackpackJourney2.png", "filename": "BagBackpackJourney2", "color1": "Brown", "color2": "Beige"}], "tags": ["Simple", "Active", "fairy tale", "outdoorsy", "work", "Orange", "Beige", "For sale", "Blue", "Brown"], "size": "", "catalog": "For sale", "hhaConcept1": "", "hhaConcept2": "", "hhaSeries": "", "hhaSet": "", "diy": "No"}, {"id": "bags-veggie-print-eco-bag-231", "name": "veggie-print eco bag", "rawCategory": "Bags", "category": "Bags", "hexBase": "3932", "image": "https://nh-cdn.catalogue.ac/FtrIcon/ToolBagEco0.png", "variants": [{"name": "Default", "hex": "3932", "hexBase": "3932", "hexVariated": "3932", "image": "https://nh-cdn.catalogue.ac/FtrIcon/ToolBagEco0.png", "filename": "ToolBagEco0", "color1": "White", "color2": "Green"}], "tags": ["Simple", "Active", "everyday", "White", "Green", "For sale"], "size": "", "catalog": "For sale", "hhaConcept1": "", "hhaConcept2": "", "hhaSeries": "", "hhaSet": "", "diy": "No"}, {"id": "bags-woven-vine-pochette-232", "name": "woven-vine pochette", "rawCategory": "Bags", "category": "Bags", "hexBase": "37A9", "image": "https://nh-cdn.catalogue.ac/ClosetIcon/BagShoulderVine0.png", "variants": [{"name": "Default", "hex": "37A9", "hexBase": "37A9", "hexVariated": "37A9", "image": "https://nh-cdn.catalogue.ac/ClosetIcon/BagShoulderVine0.png", "filename": "BagShoulderVine0", "color1": "Green", "color2": "Green"}], "tags": ["Active", "Cute", "outdoorsy", "vacation", "Green", "Not for sale", "DIY"], "size": "", "catalog": "Not for sale", "hhaConcept1": "", "hhaConcept2": "", "hhaSeries": "", "hhaSet": "", "diy": "Yes"}, {"id": "bags-zebra-print-backpack-233", "name": "zebra-print backpack", "rawCategory": "Bags", "category": "Bags", "hexBase": "02B3", "image": "https://nh-cdn.catalogue.ac/ClosetIcon/BagBackpackTownZebra0.png", "variants": [{"name": "White", "hex": "39F9", "hexBase": "02B3", "hexVariated": "39F9", "image": "https://nh-cdn.catalogue.ac/ClosetIcon/BagBackpackTownZebra0.png", "filename": "BagBackpackTownZebra0", "color1": "White", "color2": "Black"}, {"name": "Yellow", "hex": "02B3", "hexBase": "02B3", "hexVariated": "02B3", "image": "https://nh-cdn.catalogue.ac/ClosetIcon/BagBackpackTownZebra1.png", "filename": "BagBackpackTownZebra1", "color1": "Yellow", "color2": "Black"}], "tags": ["Simple", "Active", "everyday", "White", "Black", "For sale", "Yellow"], "size": "", "catalog": "For sale", "hhaConcept1": "", "hhaConcept2": "", "hhaSeries": "", "hhaSet": "", "diy": "No"}, {"id": "bags-zebra-print-shoulder-bag-234", "name": "zebra-print shoulder bag", "rawCategory": "Bags", "category": "Bags", "hexBase": "3A2F", "image": "https://nh-cdn.catalogue.ac/ClosetIcon/BagShoulderSquareZebra0.png", "variants": [{"name": "White", "hex": "3A2F", "hexBase": "3A2F", "hexVariated": "3A2F", "image": "https://nh-cdn.catalogue.ac/ClosetIcon/BagShoulderSquareZebra0.png", "filename": "BagShoulderSquareZebra0", "color1": "White", "color2": "Black"}, {"name": "Yellow", "hex": "02D6", "hexBase": "3A2F", "hexVariated": "02D6", "image": "https://nh-cdn.catalogue.ac/ClosetIcon/BagShoulderSquareZebra1.png", "filename": "BagShoulderSquareZebra1", "color1": "Yellow", "color2": "Black"}], "tags": ["Simple", "everyday", "White", "Black", "For sale", "Yellow"], "size": "", "catalog": "For sale", "hhaConcept1": "", "hhaConcept2": "", "hhaSeries": "", "hhaSet": "", "diy": "No"}, {"id": "bags-zen-clasp-purse-235", "name": "zen clasp purse", "rawCategory": "Bags", "category": "Bags", "hexBase": "0162", "image": "https://nh-cdn.catalogue.ac/ClosetIcon/BagShoulderGamaguchiJapan0.png", "variants": [{"name": "Dark blue", "hex": "3A0C", "hexBase": "0162", "hexVariated": "3A0C", "image": "https://nh-cdn.catalogue.ac/ClosetIcon/BagShoulderGamaguchiJapan0.png", "filename": "BagShoulderGamaguchiJapan0", "color1": "Blue", "color2": "Red"}, {"name": "Wisteria", "hex": "0161", "hexBase": "0162", "hexVariated": "0161", "image": "https://nh-cdn.catalogue.ac/ClosetIcon/BagShoulderGamaguchiJapan1.png", "filename": "BagShoulderGamaguchiJapan1", "color1": "Yellow", "color2": "Pink"}, {"name": "Sky blue", "hex": "0162", "hexBase": "0162", "hexVariated": "0162", "image": "https://nh-cdn.catalogue.ac/ClosetIcon/BagShoulderGamaguchiJapan2.png", "filename": "BagShoulderGamaguchiJapan2", "color1": "Aqua", "color2": "Blue"}], "tags": ["Simple", "Cute", "everyday", "Blue", "Red", "For sale", "Yellow", "Pink", "Aqua"], "size": "", "catalog": "For sale", "hhaConcept1": "", "hhaConcept2": "", "hhaSeries": "", "hhaSet": "", "diy": "No"}]